{"content":[{"id":"5e4f398e","settings":{"flex_direction":"column","boxed_width":{"unit":"px","size":1290,"sizes":[]},"flex_gap":{"column":"0","row":"0","isLinked":true,"unit":"px","size":0},"background_background":"classic","background_color":"#F5F5F5","padding":{"unit":"px","top":"20","right":"40","bottom":"20","left":"40","isLinked":false},"padding_tablet":{"unit":"px","top":"20","right":"40","bottom":"20","left":"40","isLinked":false},"padding_mobile":{"unit":"px","top":"20","right":"20","bottom":"20","left":"20","isLinked":true},"_title":"c3367","container_type":"grid","grid_columns_grid":{"unit":"custom","size":"1fr 3fr 1fr","sizes":[]},"grid_columns_grid_tablet":{"unit":"custom","size":"1fr 1fr 1fr","sizes":[]},"grid_columns_grid_mobile":{"unit":"custom","size":"3fr 1fr","sizes":[]},"grid_rows_grid":{"unit":"fr","size":1,"sizes":[]},"grid_gaps":{"column":"10","row":"10","isLinked":true,"unit":"px"},"grid_align_items":"center","presetTitle":"Grid","presetIcon":"eicon-container-grid"},"elements":[{"id":"2676e89b","settings":{"image":{"url":"https:\/\/preview.section.express\/wp-content\/uploads\/2025\/01\/logo-new-black-2.png","id":42892,"size":"","alt":"","source":"library"},"image_size":"full","link_to":"custom","link":{"url":"#","is_external":"","nofollow":"","custom_attributes":""},"align":"left","width":{"unit":"px","size":200,"sizes":[]},"width_tablet":{"unit":"px","size":"","sizes":[]},"width_mobile":{"unit":"px","size":"","sizes":[]}},"elements":[],"isInner":false,"widgetType":"image","elType":"widget"},{"id":"3373e81b","settings":{"menu_name":"Menu","menu_items":[{"item_title":"HOME","_id":"ba24edc","item_link":{"url":"#","is_external":"","nofollow":"","custom_attributes":""}},{"item_title":"MEGA MENU","_id":"bc8280c","item_dropdown_content":"yes"},{"item_title":"ABOUT","_id":"4c7a669"},{"item_title":"SERVICES","_id":"27dc11c"},{"item_title":"CONTACT","_id":"8586c60"}],"item_position_horizontal":"center","menu_item_title_space_between":{"unit":"px","size":24,"sizes":[]},"menu_item_title_typography_typography":"custom","menu_item_title_typography_font_family":"Manrope","menu_item_title_typography_font_size":{"unit":"px","size":15,"sizes":[]},"menu_item_title_typography_font_weight":"700","menu_item_title_typography_line_height":{"unit":"em","size":1,"sizes":[]},"menu_item_title_text_color_normal":"#000000","menu_item_title_text_color_hover":"#8F8F8F","menu_item_title_text_color_active":"#8F8F8F","menu_item_title_padding":{"unit":"px","top":"0","right":"0","bottom":"0","left":"0","isLinked":true},"style_menu_toggle_icon_size_tablet":{"unit":"px","size":22,"sizes":[]},"menu_toggle_icon_color_normal":"#000000","menu_toggle_icon_color_hover":"#000000","menu_toggle_icon_color_active":"#000000","content_width":"fit_to_content","item_position_horizontal_tablet":"center","toggle_align_tablet":"center","toggle_align_mobile":"flex-end","menu_item_title_space_between_tablet":{"unit":"px","size":0,"sizes":[]},"menu_item_title_distance_from_content":{"unit":"px","size":40,"sizes":[]},"menu_item_title_padding_tablet":{"unit":"px","top":"12","right":"0","bottom":"12","left":"0","isLinked":false},"menu_toggle_icon_distance_from_dropdown_tablet":{"unit":"px","size":37,"sizes":[]},"menu_toggle_icon_distance_from_dropdown_mobile":{"unit":"px","size":29,"sizes":[]},"dropdown_menu_item_text_color_normal":"#000000","dropdown_menu_item_background_color_normal_background":"classic","dropdown_menu_item_background_color_normal_color":"#FFFFFF","dropdown_menu_item_text_color_active":"#8F8F8F","dropdown_menu_item_background_color_active_background":"classic","dropdown_menu_item_background_color_active_color":"#FFFFFF","menu_item_title_distance_from_content_tablet":{"unit":"px","size":0,"sizes":[]},"content_padding_tablet":{"unit":"px","top":"0","right":"0","bottom":"0","left":"0","isLinked":true},"menu_dropdown_box_shadow_box_shadow_type":"yes","menu_dropdown_box_shadow_box_shadow":{"horizontal":0,"vertical":23,"blur":20,"spread":0,"color":"rgba(0, 0, 0, 0.04)"}},"elements":[{"id":"33aa42e4","settings":{"_title":"Item #1"},"elements":[],"isInner":true,"elType":"container","isLocked":true},{"id":"1b7941ca","settings":{"_title":"Item #2","content_width":"full","width":{"unit":"vw","size":100,"sizes":[]},"width_tablet":{"unit":"vw","size":100,"sizes":[]},"width_mobile":{"unit":"vw","size":100,"sizes":[]},"min_height_tablet":{"unit":"px","size":0,"sizes":[]},"flex_direction":"column","flex_justify_content":"flex-start","flex_gap":{"column":"0","row":"0","isLinked":true,"unit":"px","size":0},"padding":{"unit":"px","top":"0","right":"40","bottom":"0","left":"40","isLinked":false},"padding_tablet":{"unit":"px","top":"0","right":"0","bottom":"0","left":"0","isLinked":false}},"elements":[{"id":"11d5d55c","settings":{"boxed_width":{"unit":"px","size":1290,"sizes":[]},"boxed_width_tablet":{"unit":"%","size":100,"sizes":[]},"boxed_width_mobile":{"unit":"%","size":"","sizes":[]},"flex_direction":"column","flex_justify_content":"flex-start","flex_gap":{"column":"0","row":"0","isLinked":true,"unit":"px","size":0},"padding":{"unit":"px","top":"0","right":"0","bottom":"0","left":"0","isLinked":true}},"elements":[{"id":"24b1a243","settings":{"presetTitle":"Container","presetIcon":"eicon-container","content_width":"full","grid_columns_grid":{"unit":"fr","size":4,"sizes":[]},"grid_columns_grid_tablet":{"unit":"fr","size":2,"sizes":[]},"grid_rows_grid":{"unit":"fr","size":1,"sizes":[]},"grid_gaps":{"column":"50","row":"50","isLinked":true,"unit":"px"},"background_color":"#C48888","box_shadow_box_shadow_type":"yes","box_shadow_box_shadow":{"horizontal":0,"vertical":23,"blur":20,"spread":0,"color":"rgba(0, 0, 0, 0.04)"},"padding":{"unit":"px","top":"50","right":"50","bottom":"50","left":"50","isLinked":true},"padding_tablet":{"unit":"px","top":"30","right":"40","bottom":"30","left":"40","isLinked":false},"width":{"unit":"%","size":100,"sizes":[]},"width_tablet":{"unit":"vw","size":100,"sizes":[]},"width_mobile":{"unit":"vw","size":"","sizes":[]},"flex_direction":"column","flex_justify_content":"flex-start","flex_gap":{"column":"0","row":"0","isLinked":true,"unit":"px","size":0},"border_radius":{"unit":"px","top":"0","right":"0","bottom":"10","left":"10","isLinked":false},"border_radius_tablet":{"unit":"px","top":"0","right":"0","bottom":"0","left":"0","isLinked":true}},"elements":[{"id":"484079a","settings":{"container_type":"grid","presetTitle":"Grid","presetIcon":"eicon-container-grid","boxed_width":{"unit":"px","size":1290,"sizes":[]},"grid_columns_grid":{"unit":"fr","size":4,"sizes":[]},"grid_columns_grid_tablet":{"unit":"fr","size":2,"sizes":[]},"grid_rows_grid":{"unit":"fr","size":1,"sizes":[]},"grid_gaps":{"column":"30","row":"30","isLinked":true,"unit":"px"},"grid_gaps_tablet":{"column":"30","row":"30","isLinked":false,"unit":"px"},"padding":{"unit":"px","top":"0","right":"0","bottom":"0","left":"0","isLinked":true},"content_width":"full"},"elements":[{"id":"2b297150","settings":{"content_width":"full","flex_direction":"column","flex_gap":{"column":"0","row":"0","isLinked":true,"unit":"px","size":0},"background_background":"classic","background_color":"#F3F3F3","border_radius":{"unit":"px","top":"10","right":"10","bottom":"10","left":"10","isLinked":true},"padding":{"unit":"px","top":"30","right":"30","bottom":"30","left":"30","isLinked":true}},"elements":[{"id":"7cd98bb","settings":{"selected_icon":{"value":{"url":"https:\/\/preview.section.express\/wp-content\/uploads\/2024\/05\/new-layers.svg","id":57},"library":"svg"},"title_text":"Graphic Design","description_text":"Lorem dolor amet consec tetur adipis cing elit tempor.","link":{"url":"#","is_external":"","nofollow":"","custom_attributes":""},"title_size":"h5","text_align":"left","title_bottom_space":{"unit":"px","size":12,"sizes":[]},"title_color":"#000000","title_typography_typography":"custom","title_typography_font_family":"Manrope","title_typography_font_size":{"unit":"px","size":18,"sizes":[]},"title_typography_font_weight":"800","title_typography_line_height":{"unit":"em","size":1,"sizes":[]},"title_typography_letter_spacing":{"unit":"px","size":-0.4,"sizes":[]},"description_color":"#9F9F9F","description_typography_typography":"custom","description_typography_font_family":"Manrope","description_typography_font_size":{"unit":"px","size":15,"sizes":[]},"description_typography_font_weight":"400","description_typography_line_height":{"unit":"em","size":1.6,"sizes":[]},"_margin":{"unit":"px","top":"0","right":"0","bottom":"-6","left":"0","isLinked":false},"_element_width_tablet":"inherit","_element_custom_width":{"unit":"px","size":306,"sizes":[]},"icon_space":{"unit":"px","size":14,"sizes":[]},"primary_color":"#000000","icon_size":{"unit":"px","size":30,"sizes":[]}},"elements":[],"isInner":false,"widgetType":"icon-box","elType":"widget"}],"isInner":true,"elType":"container"},{"id":"521277ae","settings":{"content_width":"full","flex_direction":"column","flex_gap":{"column":"0","row":"0","isLinked":true,"unit":"px","size":0},"background_background":"classic","background_color":"#F3F3F3","border_radius":{"unit":"px","top":"10","right":"10","bottom":"10","left":"10","isLinked":true},"padding":{"unit":"px","top":"30","right":"30","bottom":"30","left":"30","isLinked":true}},"elements":[{"id":"51ac99e3","settings":{"selected_icon":{"value":{"url":"https:\/\/preview.section.express\/wp-content\/uploads\/2024\/05\/general-icons-10.svg","id":53},"library":"svg"},"title_text":"Custom Themes","description_text":"Lorem dolor amet consec tetur adipis cing elit tempor.","link":{"url":"#","is_external":"","nofollow":"","custom_attributes":""},"title_size":"h5","text_align":"left","title_bottom_space":{"unit":"px","size":12,"sizes":[]},"title_color":"#000000","title_typography_typography":"custom","title_typography_font_family":"Manrope","title_typography_font_size":{"unit":"px","size":18,"sizes":[]},"title_typography_font_weight":"800","title_typography_line_height":{"unit":"em","size":1,"sizes":[]},"title_typography_letter_spacing":{"unit":"px","size":-0.4,"sizes":[]},"description_color":"#9F9F9F","description_typography_typography":"custom","description_typography_font_family":"Manrope","description_typography_font_size":{"unit":"px","size":15,"sizes":[]},"description_typography_font_weight":"400","description_typography_line_height":{"unit":"em","size":1.6,"sizes":[]},"_margin":{"unit":"px","top":"0","right":"0","bottom":"-6","left":"0","isLinked":false},"_element_width_tablet":"inherit","_element_custom_width":{"unit":"px","size":306,"sizes":[]},"icon_space":{"unit":"px","size":14,"sizes":[]},"primary_color":"#000000","icon_size":{"unit":"px","size":30,"sizes":[]}},"elements":[],"isInner":false,"widgetType":"icon-box","elType":"widget"}],"isInner":true,"elType":"container"},{"id":"5b81ea24","settings":{"content_width":"full","flex_direction":"column","flex_gap":{"column":"0","row":"0","isLinked":true,"unit":"px","size":0},"background_background":"classic","background_color":"#F3F3F3","border_radius":{"unit":"px","top":"10","right":"10","bottom":"10","left":"10","isLinked":true},"padding":{"unit":"px","top":"30","right":"30","bottom":"30","left":"30","isLinked":true}},"elements":[{"id":"4b395e6a","settings":{"selected_icon":{"value":{"url":"https:\/\/preview.section.express\/wp-content\/uploads\/2024\/05\/general-icons-1.svg","id":48},"library":"svg"},"title_text":"Landing Pages","description_text":"Lorem dolor amet consec tetur adipis cing elit tempor.","link":{"url":"#","is_external":"","nofollow":"","custom_attributes":""},"title_size":"h5","text_align":"left","title_bottom_space":{"unit":"px","size":12,"sizes":[]},"title_color":"#000000","title_typography_typography":"custom","title_typography_font_family":"Manrope","title_typography_font_size":{"unit":"px","size":18,"sizes":[]},"title_typography_font_weight":"800","title_typography_line_height":{"unit":"em","size":1,"sizes":[]},"title_typography_letter_spacing":{"unit":"px","size":-0.4,"sizes":[]},"description_color":"#9F9F9F","description_typography_typography":"custom","description_typography_font_family":"Manrope","description_typography_font_size":{"unit":"px","size":15,"sizes":[]},"description_typography_font_weight":"400","description_typography_line_height":{"unit":"em","size":1.6,"sizes":[]},"_margin":{"unit":"px","top":"0","right":"0","bottom":"-6","left":"0","isLinked":false},"_element_width_tablet":"inherit","_element_custom_width":{"unit":"px","size":306,"sizes":[]},"icon_space":{"unit":"px","size":14,"sizes":[]},"primary_color":"#000000","icon_size":{"unit":"px","size":30,"sizes":[]}},"elements":[],"isInner":false,"widgetType":"icon-box","elType":"widget"}],"isInner":true,"elType":"container"},{"id":"8d42690","settings":{"content_width":"full","flex_direction":"column","flex_gap":{"column":"0","row":"0","isLinked":true,"unit":"px","size":0},"background_background":"classic","background_color":"#F3F3F3","border_radius":{"unit":"px","top":"10","right":"10","bottom":"10","left":"10","isLinked":true},"padding":{"unit":"px","top":"30","right":"30","bottom":"30","left":"30","isLinked":true}},"elements":[{"id":"7be5e0f9","settings":{"selected_icon":{"value":{"url":"https:\/\/preview.section.express\/wp-content\/uploads\/2024\/05\/general-icons-7.svg","id":51},"library":"svg"},"title_text":"Security Updates","description_text":"Lorem dolor amet consec tetur adipis cing elit tempor.","link":{"url":"#","is_external":"","nofollow":"","custom_attributes":""},"title_size":"h5","text_align":"left","title_bottom_space":{"unit":"px","size":12,"sizes":[]},"title_color":"#000000","title_typography_typography":"custom","title_typography_font_family":"Manrope","title_typography_font_size":{"unit":"px","size":18,"sizes":[]},"title_typography_font_weight":"800","title_typography_line_height":{"unit":"em","size":1,"sizes":[]},"title_typography_letter_spacing":{"unit":"px","size":-0.4,"sizes":[]},"description_color":"#9F9F9F","description_typography_typography":"custom","description_typography_font_family":"Manrope","description_typography_font_size":{"unit":"px","size":15,"sizes":[]},"description_typography_font_weight":"400","description_typography_line_height":{"unit":"em","size":1.6,"sizes":[]},"_margin":{"unit":"px","top":"0","right":"0","bottom":"-6","left":"0","isLinked":false},"_element_width_tablet":"inherit","_element_custom_width":{"unit":"px","size":306,"sizes":[]},"icon_space":{"unit":"px","size":14,"sizes":[]},"primary_color":"#000000","icon_size":{"unit":"px","size":30,"sizes":[]}},"elements":[],"isInner":false,"widgetType":"icon-box","elType":"widget"}],"isInner":true,"elType":"container"}],"isInner":true,"elType":"container"}],"isInner":true,"elType":"container"}],"isInner":true,"elType":"container"}],"isInner":true,"elType":"container","isLocked":true},{"id":"13feb397","settings":{"_title":"Item #3"},"elements":[],"isInner":true,"elType":"container","isLocked":true},{"id":"35e7cb58","settings":{"_title":"Item #3"},"elements":[],"isInner":true,"elType":"container","isLocked":true},{"id":"347f4eb4","settings":{"_title":"Item #3"},"elements":[],"isInner":true,"elType":"container","isLocked":true}],"isInner":false,"widgetType":"mega-menu","elType":"widget"},{"id":"723542ca","settings":{"text":"LEARN MORE","icon_indent":{"unit":"px","size":0,"sizes":[]},"typography_typography":"custom","typography_font_family":"Manrope","typography_font_size":{"unit":"px","size":15,"sizes":[]},"typography_font_weight":"800","typography_line_height":{"unit":"em","size":1,"sizes":[]},"button_text_color":"#FFFFFF","background_color":"#000000","button_background_hover_color":"#9F9F9F","button_hover_border_color":"#9F9F9F","border_border":"solid","border_width":{"unit":"px","top":"1","right":"1","bottom":"1","left":"1","isLinked":true},"border_color":"#000000","border_radius":{"unit":"px","top":"0","right":"0","bottom":"0","left":"0","isLinked":true},"text_padding":{"unit":"px","top":"19","right":"30","bottom":"20","left":"30","isLinked":false},"align":"right","hide_mobile":"hidden-mobile"},"elements":[],"isInner":false,"widgetType":"button","elType":"widget"}],"isInner":false,"elType":"container"}],"page_settings":[],"version":"0.4","title":"c3367","type":"container"}