{"content":[{"id":"7956c0ac","settings":{"flex_direction":"column","content_width":"full","flex_gap":{"column":"0","row":"0","isLinked":true,"unit":"px","size":0},"padding":{"unit":"px","top":"0","right":"0","bottom":"0","left":"0","isLinked":true},"_title":"c1134"},"elements":[{"id":"449228ca","settings":{"flex_direction":"column","boxed_width":{"unit":"px","size":1290,"sizes":[]},"flex_gap":{"column":"0","row":"0","isLinked":true,"unit":"px","size":0},"background_background":"classic","background_color":"#000000","padding":{"unit":"px","top":"120","right":"40","bottom":"278","left":"40","isLinked":false},"padding_tablet":{"unit":"px","top":"80","right":"40","bottom":"160","left":"40","isLinked":false},"padding_mobile":{"unit":"px","top":"60","right":"20","bottom":"120","left":"20","isLinked":false},"_title":"BOXED CONTAINER"},"elements":[{"id":"42a9cc35","settings":{"boxed_width":{"unit":"px","size":1290,"sizes":[]},"flex_direction":"column","flex_gap":{"column":"40","row":"40","isLinked":true,"unit":"px","size":40},"background_color":"#ECC5C5","padding":{"unit":"px","top":"0","right":"0","bottom":"0","left":"0","isLinked":true},"flex_gap_tablet":{"column":"35","row":"35","isLinked":true,"unit":"px","size":35},"flex_align_items":"center","flex_justify_content":"flex-start","animation":"fadeIn","animation_duration":"fast","animation_delay":500},"elements":[{"id":"6d12a946","settings":{"title":"Sample Subtitle","header_size":"p","title_color":"#9F9F9F","typography_typography":"custom","typography_font_family":"Manrope","typography_font_size":{"unit":"px","size":13,"sizes":[]},"typography_font_weight":"600","typography_text_transform":"uppercase","typography_line_height":{"unit":"em","size":1,"sizes":[]},"_margin":{"unit":"px","top":"-1","right":"0","bottom":"-4","left":"0","isLinked":false},"_margin_tablet":{"unit":"px","top":"-1","right":"0","bottom":"-4","left":"0","isLinked":false},"animation_duration":"fast","_animation_delay":500,"align":"center"},"elements":[],"isInner":false,"widgetType":"heading","elType":"widget"},{"id":"6c5e41b2","settings":{"title":"Corporate Branding","header_size":"h1","title_color":"#FFFFFF","typography_typography":"custom","typography_font_family":"Manrope","typography_font_size":{"unit":"px","size":70,"sizes":[]},"typography_font_size_tablet":{"unit":"px","size":42,"sizes":[]},"typography_font_size_mobile":{"unit":"px","size":38,"sizes":[]},"typography_font_weight":"900","typography_line_height":{"unit":"em","size":1.1,"sizes":[]},"typography_letter_spacing":{"unit":"px","size":-3,"sizes":[]},"typography_letter_spacing_tablet":{"unit":"px","size":-1.2,"sizes":[]},"_margin":{"unit":"px","top":"-13","right":"0","bottom":"-11","left":"0","isLinked":false},"_margin_tablet":{"unit":"px","top":"-8","right":"0","bottom":"-6","left":"0","isLinked":false},"_margin_mobile":{"unit":"px","top":"-7","right":"0","bottom":"-7","left":"0","isLinked":false},"animation_duration":"fast","_animation_delay":600,"align":"center","_element_width":"initial","_element_width_mobile":"inherit","_element_custom_width":{"unit":"px","size":719,"sizes":[]},"_element_custom_width_tablet":{"unit":"px","size":496,"sizes":[]}},"elements":[],"isInner":false,"widgetType":"heading","elType":"widget"},{"id":"772e4cd8","settings":{"editor":"<p>Sed ut unde omnis iste natus sit volur tatem accus antium laudan tium totam aperiam dicta sunt explicabo.<\/p>","text_color":"#9F9F9F","typography_typography":"custom","typography_font_family":"Manrope","typography_font_size":{"unit":"px","size":17,"sizes":[]},"typography_font_weight":"500","typography_line_height":{"unit":"em","size":1.6,"sizes":[]},"_margin":{"unit":"px","top":"-7","right":"0","bottom":"-21","left":"0","isLinked":false},"_element_width":"initial","_element_custom_width":{"unit":"px","size":538,"sizes":[]},"animation_duration":"fast","_animation_delay":700,"align":"center","_element_width_mobile":"inherit"},"elements":[],"isInner":false,"widgetType":"text-editor","elType":"widget"},{"id":"2ff2a513","settings":{"text":"Learn More","icon_indent":{"unit":"px","size":0,"sizes":[]},"typography_typography":"custom","typography_font_family":"Manrope","typography_font_size":{"unit":"px","size":15,"sizes":[]},"typography_font_weight":"800","typography_line_height":{"unit":"em","size":1,"sizes":[]},"button_text_color":"#000000","background_color":"#FFFFFF","button_background_hover_color":"#FFFFFF","button_hover_border_color":"#FFFFFF","border_border":"solid","border_width":{"unit":"px","top":"1","right":"1","bottom":"1","left":"1","isLinked":true},"border_color":"#FFFFFF","border_radius":{"unit":"px","top":"0","right":"0","bottom":"0","left":"0","isLinked":true},"text_padding":{"unit":"px","top":"20","right":"40","bottom":"20","left":"40","isLinked":false},"hover_color":"#000000","animation_duration":"fast","_animation_delay":800,"align":"center"},"elements":[],"isInner":false,"widgetType":"button","elType":"widget"}],"isInner":true,"elType":"container"}],"isInner":true,"elType":"container"},{"id":"1e54d5ae","settings":{"flex_direction":"column","boxed_width":{"unit":"px","size":1290,"sizes":[]},"flex_gap":{"column":"0","row":"0","isLinked":true,"unit":"px","size":0},"background_background":"classic","background_color":"#F5F5F5","padding":{"unit":"px","top":"0","right":"40","bottom":"120","left":"40","isLinked":false},"padding_tablet":{"unit":"px","top":"0","right":"40","bottom":"80","left":"40","isLinked":false},"padding_mobile":{"unit":"px","top":"0","right":"20","bottom":"60","left":"20","isLinked":false},"_title":"BOXED CONTAINER"},"elements":[{"id":"797fe9d2","settings":{"boxed_width":{"unit":"px","size":1290,"sizes":[]},"flex_direction":"row","flex_gap":{"column":"0","row":"0","isLinked":true,"unit":"px","size":0},"background_color":"#ECC5C5","padding":{"unit":"px","top":"0","right":"0","bottom":"0","left":"0","isLinked":true},"container_type":"grid","grid_columns_grid_tablet":{"unit":"fr","size":2,"sizes":[]},"grid_rows_grid":{"unit":"fr","size":1,"sizes":[]},"grid_gaps":{"column":"30","row":"30","isLinked":true,"unit":"px"},"presetTitle":"Grid","presetIcon":"eicon-container-grid","margin":{"unit":"px","top":"-158","right":"0","bottom":"0","left":"0","isLinked":false},"margin_tablet":{"unit":"px","top":"-80","right":"0","bottom":"0","left":"0","isLinked":false},"margin_mobile":{"unit":"px","top":"-60","right":"0","bottom":"0","left":"0","isLinked":false}},"elements":[{"id":"5c395d92","settings":{"content_width":"full","flex_direction":"column","flex_justify_content":"flex-start","flex_gap":{"column":"0","row":"0","isLinked":true,"unit":"px","size":0},"background_background":"classic","background_color":"#FFFFFF","padding":{"unit":"px","top":"50","right":"50","bottom":"30","left":"50","isLinked":false},"animation":"slideInUp","animation_duration":"fast","animation_delay":600,"box_shadow_box_shadow_type":"yes","box_shadow_box_shadow":{"horizontal":0,"vertical":1,"blur":20,"spread":0,"color":"rgba(0, 0, 0, 0.04)"}},"elements":[{"id":"5dd07c02","settings":{"selected_icon":{"value":{"url":"https:\/\/preview.section.express\/wp-content\/uploads\/2024\/05\/general-icons-10.svg","id":53},"library":"svg"},"primary_color":"#000000","size":{"unit":"px","size":45,"sizes":[]},"_margin":{"unit":"px","top":"0","right":"0","bottom":"-5","left":"0","isLinked":false},"align":"left"},"elements":[],"isInner":false,"widgetType":"icon","elType":"widget"},{"id":"47f267f8","settings":{"title":"Sample Subtitle","header_size":"p","title_color":"#9F9F9F","typography_typography":"custom","typography_font_family":"Manrope","typography_font_size":{"unit":"px","size":13,"sizes":[]},"typography_font_weight":"600","typography_text_transform":"uppercase","typography_line_height":{"unit":"em","size":1,"sizes":[]},"_margin":{"unit":"px","top":"-1","right":"0","bottom":"-4","left":"0","isLinked":false},"_margin_tablet":{"unit":"px","top":"-1","right":"0","bottom":"-4","left":"0","isLinked":false},"_padding":{"unit":"px","top":"50","right":"0","bottom":"0","left":"0","isLinked":false},"_padding_tablet":{"unit":"px","top":"50","right":"0","bottom":"0","left":"0","isLinked":false}},"elements":[],"isInner":false,"widgetType":"heading","elType":"widget"},{"id":"15dbb50b","settings":{"title":"Reality Features","header_size":"h5","title_color":"#000000","typography_typography":"custom","typography_font_family":"Manrope","typography_font_size":{"unit":"px","size":22,"sizes":[]},"typography_font_size_tablet":{"unit":"px","size":22,"sizes":[]},"typography_font_size_mobile":{"unit":"px","size":22,"sizes":[]},"typography_font_weight":"800","typography_line_height":{"unit":"em","size":1,"sizes":[]},"typography_letter_spacing":{"unit":"px","size":-0.4,"sizes":[]},"typography_letter_spacing_tablet":{"unit":"px","size":-0.4,"sizes":[]},"typography_letter_spacing_mobile":{"unit":"px","size":-0.4,"sizes":[]},"_margin":{"unit":"px","top":"-3","right":"0","bottom":"-3","left":"0","isLinked":false},"_margin_tablet":{"unit":"px","top":"-3","right":"0","bottom":"-3","left":"0","isLinked":false},"_margin_mobile":{"unit":"px","top":"-3","right":"0","bottom":"-3","left":"0","isLinked":false},"typography_text_transform":"uppercase","_padding":{"unit":"px","top":"15","right":"0","bottom":"0","left":"0","isLinked":false}},"elements":[],"isInner":false,"widgetType":"heading","elType":"widget"},{"id":"6322f21e","settings":{"text":"Divider","color":"#D8D8D8","gap":{"unit":"px","size":0,"sizes":[]},"_padding":{"unit":"px","top":"50","right":"0","bottom":"30","left":"0","isLinked":false}},"elements":[],"isInner":false,"widgetType":"divider","elType":"widget"},{"id":"a876d4b","settings":{"content_width":"full","flex_direction":"row","flex_justify_content":"space-between","flex_align_items":"center","flex_gap":{"column":"0","row":"0","isLinked":true,"unit":"px","size":0},"padding":{"unit":"px","top":"0","right":"0","bottom":"0","left":"0","isLinked":true}},"elements":[{"id":"1ff812c0","settings":{"text":"Learn More","icon_align":"right","icon_indent":{"unit":"px","size":5,"sizes":[]},"typography_typography":"custom","typography_font_family":"Manrope","typography_font_size":{"unit":"px","size":15,"sizes":[]},"typography_font_weight":"800","typography_line_height":{"unit":"em","size":1,"sizes":[]},"button_text_color":"#000000","background_color":"#00000000","hover_color":"#686868","button_background_hover_color":"#00000000","button_hover_border_color":"#000000","border_border":"none","border_width":{"unit":"px","top":"1","right":"1","bottom":"1","left":"1","isLinked":true},"border_color":"#000000","border_radius":{"unit":"px","top":"0","right":"0","bottom":"0","left":"0","isLinked":true},"text_padding":{"unit":"px","top":"0","right":"0","bottom":"0","left":"0","isLinked":true},"_margin":{"unit":"px","top":"-7","right":"0","bottom":"-6","left":"0","isLinked":false},"typography_text_transform":"uppercase"},"elements":[],"isInner":false,"widgetType":"button","elType":"widget"},{"id":"76f61ed4","settings":{"selected_icon":{"value":"fas fa-arrow-right","library":"fa-solid"},"link":{"url":"#","is_external":"","nofollow":"","custom_attributes":""},"align":"left","primary_color":"#000000","size":{"unit":"px","size":20,"sizes":[]},"_margin":{"unit":"px","top":"0","right":"0","bottom":"-7","left":"0","isLinked":false},"_element_width":"auto"},"elements":[],"isInner":false,"widgetType":"icon","elType":"widget"}],"isInner":true,"elType":"container"}],"isInner":true,"elType":"container"},{"id":"1cd4e7e7","settings":{"content_width":"full","flex_direction":"column","flex_justify_content":"flex-start","flex_gap":{"column":"0","row":"0","isLinked":true,"unit":"px","size":0},"background_background":"classic","background_color":"#FFFFFF","padding":{"unit":"px","top":"50","right":"50","bottom":"30","left":"50","isLinked":false},"animation":"slideInUp","animation_duration":"fast","animation_delay":700,"box_shadow_box_shadow_type":"yes","box_shadow_box_shadow":{"horizontal":0,"vertical":1,"blur":20,"spread":0,"color":"rgba(0, 0, 0, 0.04)"}},"elements":[{"id":"60f993d9","settings":{"selected_icon":{"value":{"url":"https:\/\/preview.section.express\/wp-content\/uploads\/2024\/05\/new-layers.svg","id":57},"library":"svg"},"primary_color":"#000000","size":{"unit":"px","size":45,"sizes":[]},"_margin":{"unit":"px","top":"0","right":"0","bottom":"-5","left":"0","isLinked":false},"align":"left"},"elements":[],"isInner":false,"widgetType":"icon","elType":"widget"},{"id":"22932075","settings":{"title":"Sample Subtitle","header_size":"p","title_color":"#9F9F9F","typography_typography":"custom","typography_font_family":"Manrope","typography_font_size":{"unit":"px","size":13,"sizes":[]},"typography_font_weight":"600","typography_text_transform":"uppercase","typography_line_height":{"unit":"em","size":1,"sizes":[]},"_margin":{"unit":"px","top":"-1","right":"0","bottom":"-4","left":"0","isLinked":false},"_margin_tablet":{"unit":"px","top":"-1","right":"0","bottom":"-4","left":"0","isLinked":false},"_padding":{"unit":"px","top":"50","right":"0","bottom":"0","left":"0","isLinked":false},"_padding_tablet":{"unit":"px","top":"50","right":"0","bottom":"0","left":"0","isLinked":false}},"elements":[],"isInner":false,"widgetType":"heading","elType":"widget"},{"id":"296dca35","settings":{"title":"Video Production","header_size":"h5","title_color":"#000000","typography_typography":"custom","typography_font_family":"Manrope","typography_font_size":{"unit":"px","size":22,"sizes":[]},"typography_font_size_tablet":{"unit":"px","size":22,"sizes":[]},"typography_font_size_mobile":{"unit":"px","size":22,"sizes":[]},"typography_font_weight":"800","typography_line_height":{"unit":"em","size":1,"sizes":[]},"typography_letter_spacing":{"unit":"px","size":-0.4,"sizes":[]},"typography_letter_spacing_tablet":{"unit":"px","size":-0.4,"sizes":[]},"typography_letter_spacing_mobile":{"unit":"px","size":-0.4,"sizes":[]},"_margin":{"unit":"px","top":"-3","right":"0","bottom":"-3","left":"0","isLinked":false},"_margin_tablet":{"unit":"px","top":"-3","right":"0","bottom":"-3","left":"0","isLinked":false},"_margin_mobile":{"unit":"px","top":"-3","right":"0","bottom":"-3","left":"0","isLinked":false},"typography_text_transform":"uppercase","_padding":{"unit":"px","top":"15","right":"0","bottom":"0","left":"0","isLinked":false}},"elements":[],"isInner":false,"widgetType":"heading","elType":"widget"},{"id":"278e8d68","settings":{"text":"Divider","color":"#D8D8D8","gap":{"unit":"px","size":0,"sizes":[]},"_padding":{"unit":"px","top":"50","right":"0","bottom":"30","left":"0","isLinked":false}},"elements":[],"isInner":false,"widgetType":"divider","elType":"widget"},{"id":"4800ef94","settings":{"content_width":"full","flex_direction":"row","flex_justify_content":"space-between","flex_align_items":"center","flex_gap":{"column":"0","row":"0","isLinked":true,"unit":"px","size":0},"padding":{"unit":"px","top":"0","right":"0","bottom":"0","left":"0","isLinked":true}},"elements":[{"id":"6195c58e","settings":{"text":"Learn More","icon_align":"right","icon_indent":{"unit":"px","size":5,"sizes":[]},"typography_typography":"custom","typography_font_family":"Manrope","typography_font_size":{"unit":"px","size":15,"sizes":[]},"typography_font_weight":"800","typography_line_height":{"unit":"em","size":1,"sizes":[]},"button_text_color":"#000000","background_color":"#00000000","hover_color":"#686868","button_background_hover_color":"#00000000","button_hover_border_color":"#000000","border_border":"none","border_width":{"unit":"px","top":"1","right":"1","bottom":"1","left":"1","isLinked":true},"border_color":"#000000","border_radius":{"unit":"px","top":"0","right":"0","bottom":"0","left":"0","isLinked":true},"text_padding":{"unit":"px","top":"0","right":"0","bottom":"0","left":"0","isLinked":true},"_margin":{"unit":"px","top":"-7","right":"0","bottom":"-6","left":"0","isLinked":false},"typography_text_transform":"uppercase"},"elements":[],"isInner":false,"widgetType":"button","elType":"widget"},{"id":"281d0dae","settings":{"selected_icon":{"value":"fas fa-arrow-right","library":"fa-solid"},"link":{"url":"#","is_external":"","nofollow":"","custom_attributes":""},"align":"left","primary_color":"#000000","size":{"unit":"px","size":20,"sizes":[]},"_margin":{"unit":"px","top":"0","right":"0","bottom":"-7","left":"0","isLinked":false},"_element_width":"auto"},"elements":[],"isInner":false,"widgetType":"icon","elType":"widget"}],"isInner":true,"elType":"container"}],"isInner":true,"elType":"container"},{"id":"57885deb","settings":{"content_width":"full","flex_direction":"column","flex_justify_content":"flex-start","flex_gap":{"column":"0","row":"0","isLinked":true,"unit":"px","size":0},"background_background":"classic","background_color":"#FFFFFF","padding":{"unit":"px","top":"50","right":"50","bottom":"30","left":"50","isLinked":false},"animation":"slideInUp","animation_duration":"fast","animation_delay":800,"box_shadow_box_shadow_type":"yes","box_shadow_box_shadow":{"horizontal":0,"vertical":1,"blur":20,"spread":0,"color":"rgba(0, 0, 0, 0.04)"}},"elements":[{"id":"3a0b09f0","settings":{"selected_icon":{"value":{"url":"https:\/\/preview.section.express\/wp-content\/uploads\/2024\/05\/general-icons-7.svg","id":51},"library":"svg"},"primary_color":"#000000","size":{"unit":"px","size":45,"sizes":[]},"_margin":{"unit":"px","top":"0","right":"0","bottom":"-5","left":"0","isLinked":false},"align":"left"},"elements":[],"isInner":false,"widgetType":"icon","elType":"widget"},{"id":"34d80989","settings":{"title":"Sample Subtitle","header_size":"p","title_color":"#9F9F9F","typography_typography":"custom","typography_font_family":"Manrope","typography_font_size":{"unit":"px","size":13,"sizes":[]},"typography_font_weight":"600","typography_text_transform":"uppercase","typography_line_height":{"unit":"em","size":1,"sizes":[]},"_margin":{"unit":"px","top":"-1","right":"0","bottom":"-4","left":"0","isLinked":false},"_margin_tablet":{"unit":"px","top":"-1","right":"0","bottom":"-4","left":"0","isLinked":false},"_padding":{"unit":"px","top":"50","right":"0","bottom":"0","left":"0","isLinked":false},"_padding_tablet":{"unit":"px","top":"50","right":"0","bottom":"0","left":"0","isLinked":false}},"elements":[],"isInner":false,"widgetType":"heading","elType":"widget"},{"id":"4282a493","settings":{"title":"Secure Payment","header_size":"h5","title_color":"#000000","typography_typography":"custom","typography_font_family":"Manrope","typography_font_size":{"unit":"px","size":22,"sizes":[]},"typography_font_size_tablet":{"unit":"px","size":22,"sizes":[]},"typography_font_size_mobile":{"unit":"px","size":22,"sizes":[]},"typography_font_weight":"800","typography_line_height":{"unit":"em","size":1,"sizes":[]},"typography_letter_spacing":{"unit":"px","size":-0.4,"sizes":[]},"typography_letter_spacing_tablet":{"unit":"px","size":-0.4,"sizes":[]},"typography_letter_spacing_mobile":{"unit":"px","size":-0.4,"sizes":[]},"_margin":{"unit":"px","top":"-3","right":"0","bottom":"-3","left":"0","isLinked":false},"_margin_tablet":{"unit":"px","top":"-3","right":"0","bottom":"-3","left":"0","isLinked":false},"_margin_mobile":{"unit":"px","top":"-3","right":"0","bottom":"-3","left":"0","isLinked":false},"typography_text_transform":"uppercase","_padding":{"unit":"px","top":"15","right":"0","bottom":"0","left":"0","isLinked":false}},"elements":[],"isInner":false,"widgetType":"heading","elType":"widget"},{"id":"75b8469e","settings":{"text":"Divider","color":"#D8D8D8","gap":{"unit":"px","size":0,"sizes":[]},"_padding":{"unit":"px","top":"50","right":"0","bottom":"30","left":"0","isLinked":false}},"elements":[],"isInner":false,"widgetType":"divider","elType":"widget"},{"id":"28701f8c","settings":{"content_width":"full","flex_direction":"row","flex_justify_content":"space-between","flex_align_items":"center","flex_gap":{"column":"0","row":"0","isLinked":true,"unit":"px","size":0},"padding":{"unit":"px","top":"0","right":"0","bottom":"0","left":"0","isLinked":true}},"elements":[{"id":"12852919","settings":{"text":"Learn More","icon_align":"right","icon_indent":{"unit":"px","size":5,"sizes":[]},"typography_typography":"custom","typography_font_family":"Manrope","typography_font_size":{"unit":"px","size":15,"sizes":[]},"typography_font_weight":"800","typography_line_height":{"unit":"em","size":1,"sizes":[]},"button_text_color":"#000000","background_color":"#00000000","hover_color":"#686868","button_background_hover_color":"#00000000","button_hover_border_color":"#000000","border_border":"none","border_width":{"unit":"px","top":"1","right":"1","bottom":"1","left":"1","isLinked":true},"border_color":"#000000","border_radius":{"unit":"px","top":"0","right":"0","bottom":"0","left":"0","isLinked":true},"text_padding":{"unit":"px","top":"0","right":"0","bottom":"0","left":"0","isLinked":true},"_margin":{"unit":"px","top":"-7","right":"0","bottom":"-6","left":"0","isLinked":false},"typography_text_transform":"uppercase"},"elements":[],"isInner":false,"widgetType":"button","elType":"widget"},{"id":"6e085ab0","settings":{"selected_icon":{"value":"fas fa-arrow-right","library":"fa-solid"},"link":{"url":"#","is_external":"","nofollow":"","custom_attributes":""},"align":"left","primary_color":"#000000","size":{"unit":"px","size":20,"sizes":[]},"_margin":{"unit":"px","top":"0","right":"0","bottom":"-7","left":"0","isLinked":false},"_element_width":"auto"},"elements":[],"isInner":false,"widgetType":"icon","elType":"widget"}],"isInner":true,"elType":"container"}],"isInner":true,"elType":"container"}],"isInner":true,"elType":"container"}],"isInner":true,"elType":"container"}],"isInner":false,"elType":"container"}],"page_settings":[],"version":"0.4","title":"c1134","type":"container"}