{"content":[{"id":"2f0138e0","settings":{"flex_direction":"column","boxed_width":{"unit":"px","size":1290,"sizes":[]},"flex_gap":{"column":"0","row":"0","isLinked":true,"unit":"px","size":0},"background_background":"classic","background_color":"#F5F5F5","padding":{"unit":"custom","top":"60vh","right":"40px","bottom":"0","left":"40px","isLinked":false},"padding_tablet":{"unit":"px","top":"250","right":"40","bottom":"0","left":"40","isLinked":false},"padding_mobile":{"unit":"px","top":"160","right":"20","bottom":"0","left":"20","isLinked":false},"_title":"c1841"},"elements":[{"id":"7d513cc0","settings":{"boxed_width":{"unit":"px","size":1290,"sizes":[]},"flex_direction":"row","flex_gap":{"column":"0","row":"0","isLinked":true,"unit":"px","size":0},"background_color":"#E2E2E2","padding":{"unit":"px","top":"70","right":"70","bottom":"70","left":"70","isLinked":true},"container_type":"grid","grid_columns_grid":{"unit":"custom","size":"2fr 1fr","sizes":[]},"grid_columns_grid_tablet":{"unit":"custom","size":"2fr 1fr","sizes":[]},"grid_rows_grid":{"unit":"fr","size":1,"sizes":[]},"grid_gaps":{"column":"50","row":"50","isLinked":true,"unit":"px"},"grid_gaps_mobile":{"column":"35","row":"35","isLinked":true,"unit":"px"},"grid_align_items":"center","background_background":"classic","padding_mobile":{"unit":"px","top":"50","right":"30","bottom":"50","left":"30","isLinked":false},"animation":"slideInLeft","animation_duration":"fast","animation_delay":500,"presetTitle":"Grid","presetIcon":"eicon-container-grid"},"elements":[{"id":"7bd9c733","settings":{"content_width":"full","flex_direction":"column","flex_justify_content":"flex-start","flex_gap":{"column":"35","row":"35","isLinked":true,"unit":"px","size":35},"flex_gap_tablet":{"column":"30","row":"30","isLinked":true,"unit":"px","size":30},"padding":{"unit":"px","top":"0","right":"0","bottom":"0","left":"0","isLinked":true}},"elements":[{"id":"5c61b73","settings":{"title":"Sample Subtitle","header_size":"p","title_color":"#9F9F9F","typography_typography":"custom","typography_font_family":"Manrope","typography_font_size":{"unit":"px","size":13,"sizes":[]},"typography_font_weight":"600","typography_text_transform":"uppercase","typography_line_height":{"unit":"em","size":1,"sizes":[]},"_margin":{"unit":"px","top":"-1","right":"0","bottom":"-4","left":"0","isLinked":false},"_margin_tablet":{"unit":"px","top":"-1","right":"0","bottom":"-4","left":"0","isLinked":false},"align_mobile":"center","content_width":"full"},"elements":[],"isInner":false,"widgetType":"heading","elType":"widget"},{"id":"356a48ca","settings":{"title":"Interface Design","header_size":"h1","title_color":"#000000","typography_typography":"custom","typography_font_family":"Manrope","typography_font_size":{"unit":"px","size":70,"sizes":[]},"typography_font_size_tablet":{"unit":"px","size":42,"sizes":[]},"typography_font_size_mobile":{"unit":"px","size":38,"sizes":[]},"typography_font_weight":"900","typography_line_height":{"unit":"em","size":1.1,"sizes":[]},"typography_letter_spacing":{"unit":"px","size":-3,"sizes":[]},"typography_letter_spacing_tablet":{"unit":"px","size":-1.2,"sizes":[]},"_margin":{"unit":"px","top":"-13","right":"0","bottom":"-11","left":"-5","isLinked":false},"_margin_tablet":{"unit":"px","top":"-8","right":"0","bottom":"-6","left":"0","isLinked":false},"_margin_mobile":{"unit":"px","top":"-7","right":"0","bottom":"-7","left":"0","isLinked":false},"align_mobile":"center","typography_text_transform":"uppercase","content_width":"full"},"elements":[],"isInner":false,"widgetType":"heading","elType":"widget"}],"isInner":true,"elType":"container"},{"id":"5ec85afa","settings":{"content_width":"full","flex_direction":"column","flex_justify_content":"flex-start","flex_gap":{"column":"35","row":"35","isLinked":true,"unit":"px","size":35},"flex_gap_tablet":{"column":"30","row":"30","isLinked":true,"unit":"px","size":30},"padding":{"unit":"px","top":"0","right":"0","bottom":"0","left":"0","isLinked":true}},"elements":[{"id":"3da47bf3","settings":{"selected_icon":{"value":"fas fa-play","library":"fa-solid"},"view":"stacked","link":{"url":"#","is_external":"","nofollow":"","custom_attributes":""},"align":"right","primary_color":"#000000","secondary_color":"#FFFFFF","size":{"unit":"px","size":20,"sizes":[]},"icon_padding":{"unit":"px","size":35,"sizes":[]},"border_width":{"unit":"px","top":"2","right":"2","bottom":"2","left":"2","isLinked":true},"border_radius":{"unit":"px","top":"0","right":"0","bottom":"0","left":"0","isLinked":true},"_margin":{"unit":"px","top":"0","right":"0","bottom":"-6","left":"0","isLinked":false},"__dynamic__":{"link":"[elementor-tag id=\"82a11ca\" name=\"lightbox\" settings=\"%7B%22type%22%3A%22video%22%2C%22video_url%22%3A%22https%3A%2F%2Fwww.youtube.com%2Fwatch%3Fv%3DYWmJWCIpXeU%22%7D\"]"},"align_mobile":"center","content_width":"full"},"elements":[],"isInner":false,"widgetType":"icon","elType":"widget"}],"isInner":true,"elType":"container"}],"isInner":true,"elType":"container"}],"isInner":false,"elType":"container"}],"page_settings":[],"version":"0.4","title":"c1841","type":"container"}