{"content":[{"id":"502f5703","settings":{"flex_direction":"column","boxed_width":{"unit":"px","size":1290,"sizes":[]},"flex_gap":{"column":"0","row":"0","isLinked":true,"unit":"px","size":0},"background_background":"classic","background_color":"#F5F5F5","padding":{"unit":"px","top":"0","right":"0","bottom":"0","left":"0","isLinked":false},"padding_tablet":{"unit":"px","top":"0","right":"0","bottom":"0","left":"0","isLinked":true},"padding_mobile":{"unit":"px","top":"0","right":"0","bottom":"0","left":"0","isLinked":true},"_title":"c1059","content_width":"full"},"elements":[{"id":"4fc6b1f5","settings":{"boxed_width":{"unit":"px","size":1290,"sizes":[]},"flex_direction":"column","flex_justify_content":"space-between","flex_align_items":"center","flex_gap":{"column":"0","row":"0","isLinked":true,"unit":"px","size":0},"flex_gap_mobile":{"column":"0","row":"0","isLinked":true,"unit":"px","size":0},"padding":{"unit":"px","top":"0","right":"40","bottom":"0","left":"40","isLinked":false},"padding_tablet":{"unit":"px","top":"0","right":"40","bottom":"0","left":"40","isLinked":false},"padding_mobile":{"unit":"px","top":"0","right":"20","bottom":"0","left":"20","isLinked":false}},"elements":[{"id":"56fc5ee2","settings":{"content_width":"full","flex_direction":"row","flex_justify_content":"space-between","flex_gap":{"column":"10","row":"10","isLinked":true,"unit":"px","size":10},"border_border":"none","border_width":{"unit":"px","top":"0","right":"0","bottom":"1","left":"0","isLinked":false},"border_color":"#D8D8D8","padding":{"unit":"px","top":"20","right":"0","bottom":"20","left":"0","isLinked":false},"flex_direction_mobile":"row","flex_justify_content_mobile":"center","flex_align_items":"center"},"elements":[{"id":"7bd1ad79","settings":{"title":"demo@section.express","header_size":"p","title_color":"#000000","typography_typography":"custom","typography_font_family":"Manrope","typography_font_size":{"unit":"px","size":14,"sizes":[]},"typography_font_weight":"900","typography_line_height":{"unit":"em","size":1,"sizes":[]},"_margin":{"unit":"px","top":"-2","right":"0","bottom":"-3","left":"0","isLinked":false},"align_mobile":"center"},"elements":[],"isInner":false,"widgetType":"heading","elType":"widget"},{"id":"77d2f650","settings":{"title":"Sed ut unde omnis iste natus sit volur tatem accus antium.","header_size":"p","title_color":"#000000","typography_typography":"custom","typography_font_family":"Manrope","typography_font_size":{"unit":"px","size":14,"sizes":[]},"typography_font_weight":"500","typography_line_height":{"unit":"em","size":1,"sizes":[]},"_margin":{"unit":"px","top":"-2","right":"0","bottom":"-3","left":"0","isLinked":false},"hide_mobile":"hidden-mobile"},"elements":[],"isInner":false,"widgetType":"heading","elType":"widget"}],"isInner":true,"elType":"container"},{"id":"5ea8c443","settings":{"text":"Divider","color":"#D8D8D8","gap":{"unit":"px","size":0,"sizes":[]},"_padding":{"unit":"px","top":"0","right":"0","bottom":"0","left":"0","isLinked":false}},"elements":[],"isInner":false,"widgetType":"divider","elType":"widget"},{"id":"5783aa14","settings":{"content_width":"full","flex_direction":"column","flex_gap":{"column":"0","row":"0","isLinked":true,"unit":"px","size":0},"padding":{"unit":"px","top":"30","right":"0","bottom":"30","left":"0","isLinked":false},"padding_mobile":{"unit":"px","top":"20","right":"0","bottom":"20","left":"0","isLinked":false},"container_type":"grid","grid_columns_grid":{"unit":"custom","size":"3fr 1fr","sizes":[]},"grid_columns_grid_tablet":{"unit":"custom","size":"1fr 1fr","sizes":[]},"grid_columns_grid_mobile":{"unit":"custom","size":"1fr 1fr","sizes":[]},"grid_rows_grid":{"unit":"fr","size":1,"sizes":[]},"grid_gaps":{"column":"5","row":"5","isLinked":true,"unit":"px"},"grid_align_items":"center","presetTitle":"Grid","presetIcon":"eicon-container-grid"},"elements":[{"id":"e2a7219","settings":{"content_width":"full","flex_direction":"row","flex_justify_content":"flex-start","flex_align_items":"center","flex_gap":{"column":"50","row":"50","isLinked":true,"unit":"px","size":50},"flex_gap_tablet":{"column":"20","row":"20","isLinked":true,"unit":"px","size":20},"padding":{"unit":"px","top":"0","right":"0","bottom":"0","left":"0","isLinked":true}},"elements":[{"id":"3d519209","settings":{"image":{"url":"https:\/\/preview.section.express\/wp-content\/uploads\/2024\/05\/king-logo-dark.png","id":42,"size":"","alt":"","source":"library"},"image_size":"custom","image_custom_dimension":{"width":"65","height":""},"link_to":"custom","link":{"url":"#","is_external":"","nofollow":"","custom_attributes":""},"align":"left"},"elements":[],"isInner":false,"widgetType":"image","elType":"widget"},{"id":"5bb5be5c","settings":{"menu_items":[{"item_title":"Home","item_link":{"url":"#","is_external":"","nofollow":"","custom_attributes":""},"_id":"be67950"},{"item_title":"About","item_link":{"url":"#","is_external":"","nofollow":"","custom_attributes":""},"_id":"f88533e"},{"item_title":"Services","item_link":{"url":"#","is_external":"","nofollow":"","custom_attributes":""},"item_dropdown_content":"yes","_id":"0c095fd"},{"item_title":"Portfolio","item_link":{"url":"#","is_external":"","nofollow":"","custom_attributes":""},"_id":"38c7c16"},{"item_title":"Our Team","item_link":{"url":"#","is_external":"","nofollow":"","custom_attributes":""},"_id":"bdc5b8d"},{"item_title":"Contact","item_link":{"url":"#","is_external":"","nofollow":"","custom_attributes":""},"_id":"466a7b2"}],"content_width":"fit_to_content","content_horizontal_position":"left","menu_item_title_space_between":{"unit":"px","size":25,"sizes":[]},"menu_item_title_typography_typography":"custom","menu_item_title_typography_font_family":"Manrope","menu_item_title_typography_font_size":{"unit":"px","size":14,"sizes":[]},"menu_item_title_typography_font_weight":"900","menu_item_title_typography_text_transform":"uppercase","menu_item_title_typography_line_height":{"unit":"em","size":1,"sizes":[]},"menu_item_title_text_color_normal":"#000000","menu_item_title_text_color_hover":"#B3B3B3","menu_item_title_padding":{"unit":"px","top":"0","right":"0","bottom":"0","left":"0","isLinked":true},"menu_item_title_distance_from_content":{"unit":"px","size":25,"sizes":[]},"hide_tablet":"hidden-tablet","hide_mobile":"hidden-mobile"},"elements":[{"id":"254f76de","settings":{"_title":"Item #1"},"elements":[],"isInner":true,"elType":"container","isLocked":true},{"id":"16d154a9","settings":{"_title":"Item #1"},"elements":[],"isInner":true,"elType":"container","isLocked":true},{"id":"23232071","settings":{"_title":"Item #1","content_width":"full","width":{"unit":"px","size":225,"sizes":[]},"background_background":"classic","background_color":"#FFFFFF","box_shadow_box_shadow_type":"yes","box_shadow_box_shadow":{"horizontal":0,"vertical":1,"blur":20,"spread":0,"color":"rgba(0, 0, 0, 0.04)"},"padding":{"unit":"px","top":"35","right":"35","bottom":"35","left":"35","isLinked":false}},"elements":[{"id":"1704e27","settings":{"icon_list":[{"text":"Online Stores","selected_icon":{"value":"","library":""},"_id":"e66cc8b","link":{"url":"#","is_external":"","nofollow":"","custom_attributes":""}},{"text":"Visual Design","selected_icon":{"value":"","library":""},"link":{"url":"#","is_external":"","nofollow":"","custom_attributes":""},"_id":"82b8f17"},{"text":"User Interface","selected_icon":{"value":"","library":""},"link":{"url":"#","is_external":"","nofollow":"","custom_attributes":""},"_id":"210f3c2"},{"text":"Business Email","selected_icon":{"value":"","library":""},"link":{"url":"#","is_external":"","nofollow":"","custom_attributes":""},"_id":"53526f9"},{"text":"Social Media","selected_icon":{"value":"","library":""},"link":{"url":"#","is_external":"","nofollow":"","custom_attributes":""},"_id":"1ff2e4c"},{"text":"Domain Name","selected_icon":{"value":"","library":""},"link":{"url":"#","is_external":"","nofollow":"","custom_attributes":""},"_id":"2e8ff2a"}],"space_between":{"unit":"px","size":18,"sizes":[]},"icon_typography_typography":"custom","icon_typography_font_family":"Manrope","icon_typography_font_size":{"unit":"px","size":14,"sizes":[]},"icon_typography_font_weight":"600","icon_typography_line_height":{"unit":"em","size":1,"sizes":[]},"text_color":"#000000","text_color_hover":"#B3B3B3","link_click":"inline","icon_typography_text_transform":"uppercase"},"elements":[],"isInner":false,"widgetType":"icon-list","elType":"widget"}],"isInner":true,"elType":"container","isLocked":true},{"id":"5436b60e","settings":{"_title":"Item #1"},"elements":[],"isInner":true,"elType":"container","isLocked":true},{"id":"446d2a8c","settings":{"_title":"Item #1"},"elements":[],"isInner":true,"elType":"container","isLocked":true},{"id":"4b2408db","settings":{"_title":"Item #1"},"elements":[],"isInner":true,"elType":"container","isLocked":true}],"isInner":false,"widgetType":"mega-menu","elType":"widget"},{"id":"61ebe952","settings":{"selected_icon":{"value":{"url":"https:\/\/preview.section.express\/wp-content\/uploads\/2024\/05\/menu-burger.svg","id":55},"library":"svg"},"primary_color":"#000000","hover_primary_color":"#B3B3B3","size":{"unit":"px","size":24,"sizes":[]},"_margin":{"unit":"px","top":"-3","right":"0","bottom":"-10","left":"0","isLinked":false},"__dynamic__":{"link":"[elementor-tag id=\"6f40c74\" name=\"popup\" settings=\"%7B%22popup%22%3A%2211773%22%7D\"]"},"hide_desktop":"hidden-desktop"},"elements":[],"isInner":false,"widgetType":"icon","elType":"widget"}],"isInner":true,"elType":"container"},{"id":"6f12a99a","settings":{"social_icon_list":[{"social_icon":{"value":"fab fa-facebook","library":"fa-brands"},"_id":"84de456"},{"social_icon":{"value":"fab fa-vk","library":"fa-brands"},"_id":"f374be3"},{"social_icon":{"value":"fab fa-youtube","library":"fa-brands"},"_id":"5109730"},{"social_icon":{"value":"fab fa-behance","library":"fa-brands"},"_id":"ccce1f7"}],"shape":"circle","align":"right","icon_color":"custom","icon_primary_color":"#02010100","icon_secondary_color":"#000000","icon_size":{"unit":"px","size":18,"sizes":[]},"icon_padding":{"unit":"em","size":0,"sizes":[]},"icon_spacing":{"unit":"px","size":17,"sizes":[]},"image_border_border":"none","hover_secondary_color":"#B3B3B3"},"elements":[],"isInner":false,"widgetType":"social-icons","elType":"widget"}],"isInner":true,"elType":"container"}],"isInner":true,"elType":"container"}],"isInner":false,"elType":"container"}],"page_settings":[],"version":"0.4","title":"c1059","type":"container"}