{"content":[{"id":"5284b36f","settings":{"flex_direction":"column","boxed_width":{"unit":"px","size":1290,"sizes":[]},"flex_gap":{"column":"0","row":"0","isLinked":true,"unit":"px","size":0},"background_color":"#0C0C0C","padding":{"unit":"px","top":"0","right":"0","bottom":"0","left":"0","isLinked":true},"padding_tablet":{"unit":"px","top":"0","right":"0","bottom":"0","left":"0","isLinked":true},"padding_mobile":{"unit":"px","top":"0","right":"0","bottom":"0","left":"0","isLinked":true},"_title":"c2557","content_width":"full","flex_justify_content":"flex-start"},"elements":[{"id":"4441196f","settings":{"content_width":"full","carousel_items":[{"slide_title":"Slide #1","_id":"d321a37"},{"slide_title":"Slide #1","_id":"2e41fcc"}],"slides_to_show":"1","slides_to_scroll":"1","navigation_previous_icon_horizontal_position":{"unit":"px","size":35,"sizes":[]},"navigation_next_icon_horizontal_position":{"unit":"px","size":35,"sizes":[]},"image_spacing_custom":{"unit":"px","size":0,"sizes":[]},"content_border_border":"none","border_radius":{"unit":"px","top":"0","right":"0","bottom":"0","left":"0","isLinked":true},"content_padding":{"unit":"px","top":"0","right":"0","bottom":"0","left":"0","isLinked":true},"arrows_size":{"unit":"px","size":25,"sizes":[]},"arrow_normal_color":"#FFFFFF","arrow_hover_color":"#FFFFFF","dots_size":{"unit":"px","size":6,"sizes":[]},"dots_normal_color":"#FFFFFF","dots_hover_color":"#F0F0F0","dots_pagination_spacing":{"unit":"px","size":50,"sizes":[]},"_padding":{"unit":"px","top":"0","right":"0","bottom":"0","left":"0","isLinked":true},"slides_to_show_tablet":"1","image_spacing_custom_tablet":{"unit":"px","size":0,"sizes":[]},"image_spacing_custom_mobile":{"unit":"px","size":0,"sizes":[]},"arrows_border_radius":{"unit":"px","top":"0","right":"0","bottom":"0","left":"0","isLinked":true},"arrows_padding":{"unit":"px","top":"0","right":"0","bottom":"0","left":"0","isLinked":true},"dots_custom_position":"yes","dots_vertical_offset":{"unit":"px","size":-35,"sizes":[]},"dots_vertical_offset_tablet":{"unit":"px","size":-30,"sizes":[]},"dots_vertical_offset_mobile":{"unit":"px","size":-25,"sizes":[]},"dots_position":"inside","pagination":""},"elements":[{"id":"616969b9","settings":{"_title":"Slide #1","content_width":"full","flex_direction":"column","flex_justify_content":"flex-start","flex_gap":{"column":"0","row":"0","isLinked":true,"unit":"px","size":0},"padding":{"unit":"px","top":"0","right":"0","bottom":"0","left":"0","isLinked":true}},"elements":[{"id":"40219f84","settings":{"flex_direction":"column","boxed_width":{"unit":"px","size":1290,"sizes":[]},"flex_gap":{"column":"120","row":"120","isLinked":true,"unit":"px","size":120},"background_background":"classic","background_color":"#000000","padding":{"unit":"px","top":"120","right":"40","bottom":"60","left":"40","isLinked":false},"padding_tablet":{"unit":"px","top":"80","right":"40","bottom":"60","left":"40","isLinked":false},"padding_mobile":{"unit":"px","top":"60","right":"20","bottom":"40","left":"20","isLinked":false},"_title":"c1267","flex_gap_tablet":{"column":"60","row":"60","isLinked":true,"unit":"px","size":60},"flex_gap_mobile":{"column":"50","row":"50","isLinked":true,"unit":"px","size":50}},"elements":[{"id":"3f88e3b7","settings":{"boxed_width":{"unit":"px","size":1290,"sizes":[]},"flex_direction":"column","flex_gap":{"column":"40","row":"40","isLinked":true,"unit":"px","size":40},"background_color":"#ECC5C5","padding":{"unit":"px","top":"0","right":"0","bottom":"0","left":"0","isLinked":true},"flex_justify_content":"flex-start","flex_align_items":"center","flex_gap_tablet":{"column":"30","row":"30","isLinked":true,"unit":"px","size":30},"animation":"fadeIn","animation_duration":"fast","animation_delay":500},"elements":[{"id":"4a6f6555","settings":{"title":"Sample Subtitle","header_size":"p","title_color":"#9F9F9F","typography_typography":"custom","typography_font_family":"Manrope","typography_font_size":{"unit":"px","size":13,"sizes":[]},"typography_font_weight":"600","typography_text_transform":"uppercase","typography_line_height":{"unit":"em","size":1,"sizes":[]},"_margin":{"unit":"px","top":"0","right":"0","bottom":"-4","left":"0","isLinked":false},"_margin_tablet":{"unit":"px","top":"0","right":"0","bottom":"-4","left":"0","isLinked":false},"align":"center","content_width":"full"},"elements":[],"isInner":false,"widgetType":"heading","elType":"widget"},{"id":"652d6442","settings":{"title":"Visual clarity improves user satisfaction.","header_size":"h1","title_color":"#FFFFFF","typography_typography":"custom","typography_font_family":"Manrope","typography_font_size":{"unit":"px","size":70,"sizes":[]},"typography_font_size_tablet":{"unit":"px","size":42,"sizes":[]},"typography_font_size_mobile":{"unit":"px","size":38,"sizes":[]},"typography_font_weight":"900","typography_line_height":{"unit":"em","size":1.1,"sizes":[]},"typography_letter_spacing":{"unit":"px","size":-3,"sizes":[]},"typography_letter_spacing_tablet":{"unit":"px","size":-1.2,"sizes":[]},"_margin":{"unit":"px","top":"-13","right":"0","bottom":"-11","left":"0","isLinked":false},"_margin_tablet":{"unit":"px","top":"-8","right":"0","bottom":"-6","left":"0","isLinked":false},"_margin_mobile":{"unit":"px","top":"-7","right":"0","bottom":"-7","left":"0","isLinked":false},"align":"center","content_width":"full","_element_width":"initial","_element_width_mobile":"inherit","_element_custom_width":{"unit":"px","size":788,"sizes":[]},"_element_custom_width_tablet":{"unit":"px","size":480,"sizes":[]}},"elements":[],"isInner":false,"widgetType":"heading","elType":"widget"},{"id":"1c83dfbc","settings":{"editor":"<p>Amnis iste natus sit volur tatem accus antium laudan tium totam rem aperiam eaque ipsa ab illo inventore veritatis.<\/p>","text_color":"#9F9F9F","typography_typography":"custom","typography_font_family":"Manrope","typography_font_size":{"unit":"px","size":17,"sizes":[]},"typography_font_weight":"500","typography_line_height":{"unit":"em","size":1.6,"sizes":[]},"_margin":{"unit":"px","top":"-7","right":"0","bottom":"-21","left":"0","isLinked":false},"align":"center","_element_width":"initial","_element_custom_width":{"unit":"px","size":553,"sizes":[]},"content_width":"full"},"elements":[],"isInner":false,"widgetType":"text-editor","elType":"widget"},{"id":"6ae5258","settings":{"content_width":"full","flex_direction":"row","flex_justify_content":"center","flex_align_items":"center","flex_gap":{"column":"20","row":"20","isLinked":true,"unit":"px","size":20},"padding":{"unit":"px","top":"0","right":"0","bottom":"0","left":"0","isLinked":true}},"elements":[{"id":"3c5a9f","settings":{"text":"Support","icon_indent":{"unit":"px","size":0,"sizes":[]},"typography_typography":"custom","typography_font_family":"Manrope","typography_font_size":{"unit":"px","size":15,"sizes":[]},"typography_font_weight":"800","typography_line_height":{"unit":"em","size":1,"sizes":[]},"button_text_color":"#FFFFFF","background_color":"#00000000","hover_color":"#000000","button_background_hover_color":"#FFFFFF","button_hover_border_color":"#FFFFFF","border_border":"solid","border_width":{"unit":"px","top":"1","right":"1","bottom":"1","left":"1","isLinked":true},"border_color":"#FFFFFF","border_radius":{"unit":"px","top":"0","right":"0","bottom":"0","left":"0","isLinked":true},"text_padding":{"unit":"px","top":"20","right":"40","bottom":"20","left":"40","isLinked":false},"content_width":"full"},"elements":[],"isInner":false,"widgetType":"button","elType":"widget"},{"id":"79494194","settings":{"text":"Learn More","icon_indent":{"unit":"px","size":0,"sizes":[]},"typography_typography":"custom","typography_font_family":"Manrope","typography_font_size":{"unit":"px","size":15,"sizes":[]},"typography_font_weight":"800","typography_line_height":{"unit":"em","size":1,"sizes":[]},"button_text_color":"#000000","background_color":"#FFFFFF","button_background_hover_color":"#9F9F9F00","button_hover_border_color":"#FFFFFF","border_border":"solid","border_width":{"unit":"px","top":"1","right":"1","bottom":"1","left":"1","isLinked":true},"border_color":"#FFFFFF","border_radius":{"unit":"px","top":"0","right":"0","bottom":"0","left":"0","isLinked":true},"text_padding":{"unit":"px","top":"20","right":"40","bottom":"20","left":"40","isLinked":false},"content_width":"full","hover_color":"#FFFFFF"},"elements":[],"isInner":false,"widgetType":"button","elType":"widget"}],"isInner":true,"elType":"container"}],"isInner":true,"elType":"container"},{"id":"f079047","settings":{"boxed_width":{"unit":"px","size":1290,"sizes":[]},"flex_direction":"column","flex_gap":{"column":"35","row":"35","isLinked":true,"unit":"px","size":35},"background_color":"#ECC5C5","padding":{"unit":"px","top":"0","right":"0","bottom":"0","left":"0","isLinked":true},"content_width":"full","flex_justify_content":"flex-start","flex_align_items":"center","flex_gap_tablet":{"column":"30","row":"30","isLinked":true,"unit":"px","size":30},"animation":"fadeIn","animation_duration":"fast","animation_delay":750},"elements":[{"id":"6d0836ab","settings":{"title":"WORKING WITH","header_size":"h5","title_color":"#FFFFFF","typography_typography":"custom","typography_font_family":"Manrope","typography_font_size":{"unit":"px","size":22,"sizes":[]},"typography_font_size_tablet":{"unit":"px","size":22,"sizes":[]},"typography_font_size_mobile":{"unit":"px","size":22,"sizes":[]},"typography_font_weight":"800","typography_line_height":{"unit":"em","size":1,"sizes":[]},"typography_letter_spacing":{"unit":"px","size":-0.4,"sizes":[]},"typography_letter_spacing_tablet":{"unit":"px","size":-0.4,"sizes":[]},"typography_letter_spacing_mobile":{"unit":"px","size":-0.4,"sizes":[]},"_margin":{"unit":"px","top":"-3","right":"0","bottom":"-3","left":"0","isLinked":false},"_margin_tablet":{"unit":"px","top":"-3","right":"0","bottom":"-3","left":"0","isLinked":false},"_margin_mobile":{"unit":"px","top":"-3","right":"0","bottom":"-3","left":"0","isLinked":false},"content_width":"full"},"elements":[],"isInner":false,"widgetType":"heading","elType":"widget"},{"id":"686ae831","settings":{"text":"Divider","color":"#FFFFFF42","gap":{"unit":"px","size":0,"sizes":[]},"content_width":"full"},"elements":[],"isInner":false,"widgetType":"divider","elType":"widget"},{"id":"10d2e44a","settings":{"container_type":"grid","presetTitle":"Grid","presetIcon":"eicon-container-grid","content_width":"full","grid_columns_grid":{"unit":"fr","size":6,"sizes":[]},"grid_columns_grid_mobile":{"unit":"fr","size":2,"sizes":[]},"grid_rows_grid":{"unit":"fr","size":1,"sizes":[]},"grid_gaps":{"column":"20","row":"20","isLinked":true,"unit":"px"},"grid_gaps_tablet":{"column":"20","row":"20","isLinked":true,"unit":"px"},"grid_justify_items":"center","grid_align_items":"center","padding":{"unit":"px","top":"0","right":"0","bottom":"0","left":"0","isLinked":true}},"elements":[{"id":"69181bb9","settings":{"content_width":"full","image":{"url":"https:\/\/preview.section.express\/wp-content\/uploads\/2024\/05\/logo-container-1.png","id":1420,"size":"","alt":"","source":"library"},"image_size":"custom","image_custom_dimension":{"width":"120","height":""},"align":"center"},"elements":[],"isInner":false,"widgetType":"image","elType":"widget"},{"id":"1dfb0e9e","settings":{"content_width":"full","image":{"url":"https:\/\/preview.section.express\/wp-content\/uploads\/2024\/05\/logo-container-2.png","id":1421,"size":"","alt":"","source":"library"},"image_size":"custom","image_custom_dimension":{"width":"120","height":""},"align":"center"},"elements":[],"isInner":false,"widgetType":"image","elType":"widget"},{"id":"357fb97f","settings":{"content_width":"full","image":{"url":"https:\/\/preview.section.express\/wp-content\/uploads\/2024\/05\/logo-container-3.png","id":1422,"size":"","alt":"","source":"library"},"image_size":"custom","image_custom_dimension":{"width":"120","height":""},"align":"center"},"elements":[],"isInner":false,"widgetType":"image","elType":"widget"},{"id":"4b3264b2","settings":{"content_width":"full","image":{"url":"https:\/\/preview.section.express\/wp-content\/uploads\/2024\/05\/logo-container-4.png","id":1423,"size":"","alt":"","source":"library"},"image_size":"custom","image_custom_dimension":{"width":"120","height":""},"align":"center"},"elements":[],"isInner":false,"widgetType":"image","elType":"widget"},{"id":"464d1e49","settings":{"content_width":"full","image":{"url":"https:\/\/preview.section.express\/wp-content\/uploads\/2024\/05\/logo-container-5.png","id":1424,"size":"","alt":"","source":"library"},"image_size":"custom","image_custom_dimension":{"width":"120","height":""},"align":"center"},"elements":[],"isInner":false,"widgetType":"image","elType":"widget"},{"id":"5bd00823","settings":{"content_width":"full","image":{"url":"https:\/\/preview.section.express\/wp-content\/uploads\/2024\/05\/logo-container-6.png","id":1425,"size":"","alt":"","source":"library"},"image_size":"custom","image_custom_dimension":{"width":"120","height":""},"align":"center"},"elements":[],"isInner":false,"widgetType":"image","elType":"widget"}],"isInner":true,"elType":"container"}],"isInner":true,"elType":"container"}],"isInner":true,"elType":"container"}],"isInner":true,"elType":"container","isLocked":true},{"id":"4083cbef","settings":{"_title":"Slide #1","content_width":"full","flex_direction":"column","flex_justify_content":"flex-start","flex_gap":{"column":"0","row":"0","isLinked":true,"unit":"px","size":0},"padding":{"unit":"px","top":"0","right":"0","bottom":"0","left":"0","isLinked":true}},"elements":[{"id":"726cd3a8","settings":{"flex_direction":"column","boxed_width":{"unit":"px","size":1290,"sizes":[]},"flex_gap":{"column":"120","row":"120","isLinked":true,"unit":"px","size":120},"background_background":"classic","background_color":"#363636","padding":{"unit":"px","top":"120","right":"40","bottom":"60","left":"40","isLinked":false},"padding_tablet":{"unit":"px","top":"80","right":"40","bottom":"60","left":"40","isLinked":false},"padding_mobile":{"unit":"px","top":"60","right":"20","bottom":"40","left":"20","isLinked":false},"_title":"c1267","flex_gap_tablet":{"column":"60","row":"60","isLinked":true,"unit":"px","size":60},"flex_gap_mobile":{"column":"50","row":"50","isLinked":true,"unit":"px","size":50}},"elements":[{"id":"655c41bf","settings":{"boxed_width":{"unit":"px","size":1290,"sizes":[]},"flex_direction":"column","flex_gap":{"column":"40","row":"40","isLinked":true,"unit":"px","size":40},"background_color":"#ECC5C5","padding":{"unit":"px","top":"0","right":"0","bottom":"0","left":"0","isLinked":true},"flex_justify_content":"flex-start","flex_align_items":"center","flex_gap_tablet":{"column":"30","row":"30","isLinked":true,"unit":"px","size":30},"animation":"fadeIn","animation_duration":"fast","animation_delay":500},"elements":[{"id":"56472500","settings":{"title":"Sample Subtitle","header_size":"p","title_color":"#9F9F9F","typography_typography":"custom","typography_font_family":"Manrope","typography_font_size":{"unit":"px","size":13,"sizes":[]},"typography_font_weight":"600","typography_text_transform":"uppercase","typography_line_height":{"unit":"em","size":1,"sizes":[]},"_margin":{"unit":"px","top":"0","right":"0","bottom":"-4","left":"0","isLinked":false},"_margin_tablet":{"unit":"px","top":"0","right":"0","bottom":"-4","left":"0","isLinked":false},"align":"center","content_width":"full"},"elements":[],"isInner":false,"widgetType":"heading","elType":"widget"},{"id":"3002ba33","settings":{"title":"Flexible designs adapt to user needs.","header_size":"h1","title_color":"#FFFFFF","typography_typography":"custom","typography_font_family":"Manrope","typography_font_size":{"unit":"px","size":70,"sizes":[]},"typography_font_size_tablet":{"unit":"px","size":42,"sizes":[]},"typography_font_size_mobile":{"unit":"px","size":38,"sizes":[]},"typography_font_weight":"900","typography_line_height":{"unit":"em","size":1.1,"sizes":[]},"typography_letter_spacing":{"unit":"px","size":-3,"sizes":[]},"typography_letter_spacing_tablet":{"unit":"px","size":-1.2,"sizes":[]},"_margin":{"unit":"px","top":"-13","right":"0","bottom":"-11","left":"0","isLinked":false},"_margin_tablet":{"unit":"px","top":"-8","right":"0","bottom":"-6","left":"0","isLinked":false},"_margin_mobile":{"unit":"px","top":"-7","right":"0","bottom":"-7","left":"0","isLinked":false},"align":"center","content_width":"full","_element_width":"initial","_element_width_mobile":"inherit","_element_custom_width":{"unit":"px","size":743,"sizes":[]},"_element_custom_width_tablet":{"unit":"px","size":480,"sizes":[]}},"elements":[],"isInner":false,"widgetType":"heading","elType":"widget"},{"id":"7e871f08","settings":{"editor":"<p>Amnis iste natus sit volur tatem accus antium laudan tium totam rem aperiam eaque ipsa ab illo inventore veritatis.<\/p>","text_color":"#9F9F9F","typography_typography":"custom","typography_font_family":"Manrope","typography_font_size":{"unit":"px","size":17,"sizes":[]},"typography_font_weight":"500","typography_line_height":{"unit":"em","size":1.6,"sizes":[]},"_margin":{"unit":"px","top":"-7","right":"0","bottom":"-21","left":"0","isLinked":false},"align":"center","_element_width":"initial","_element_custom_width":{"unit":"px","size":553,"sizes":[]},"content_width":"full"},"elements":[],"isInner":false,"widgetType":"text-editor","elType":"widget"},{"id":"551168ee","settings":{"content_width":"full","flex_direction":"row","flex_justify_content":"center","flex_align_items":"center","flex_gap":{"column":"20","row":"20","isLinked":true,"unit":"px","size":20},"padding":{"unit":"px","top":"0","right":"0","bottom":"0","left":"0","isLinked":true}},"elements":[{"id":"216351c7","settings":{"text":"Support","icon_indent":{"unit":"px","size":0,"sizes":[]},"typography_typography":"custom","typography_font_family":"Manrope","typography_font_size":{"unit":"px","size":15,"sizes":[]},"typography_font_weight":"800","typography_line_height":{"unit":"em","size":1,"sizes":[]},"button_text_color":"#FFFFFF","background_color":"#00000000","hover_color":"#000000","button_background_hover_color":"#FFFFFF","button_hover_border_color":"#FFFFFF","border_border":"solid","border_width":{"unit":"px","top":"1","right":"1","bottom":"1","left":"1","isLinked":true},"border_color":"#FFFFFF","border_radius":{"unit":"px","top":"0","right":"0","bottom":"0","left":"0","isLinked":true},"text_padding":{"unit":"px","top":"20","right":"40","bottom":"20","left":"40","isLinked":false},"content_width":"full"},"elements":[],"isInner":false,"widgetType":"button","elType":"widget"},{"id":"19db9e03","settings":{"text":"Learn More","icon_indent":{"unit":"px","size":0,"sizes":[]},"typography_typography":"custom","typography_font_family":"Manrope","typography_font_size":{"unit":"px","size":15,"sizes":[]},"typography_font_weight":"800","typography_line_height":{"unit":"em","size":1,"sizes":[]},"button_text_color":"#000000","background_color":"#FFFFFF","button_background_hover_color":"#9F9F9F00","button_hover_border_color":"#FFFFFF","border_border":"solid","border_width":{"unit":"px","top":"1","right":"1","bottom":"1","left":"1","isLinked":true},"border_color":"#FFFFFF","border_radius":{"unit":"px","top":"0","right":"0","bottom":"0","left":"0","isLinked":true},"text_padding":{"unit":"px","top":"20","right":"40","bottom":"20","left":"40","isLinked":false},"content_width":"full","hover_color":"#FFFFFF"},"elements":[],"isInner":false,"widgetType":"button","elType":"widget"}],"isInner":true,"elType":"container"}],"isInner":true,"elType":"container"},{"id":"4f34c6ad","settings":{"boxed_width":{"unit":"px","size":1290,"sizes":[]},"flex_direction":"column","flex_gap":{"column":"35","row":"35","isLinked":true,"unit":"px","size":35},"background_color":"#ECC5C5","padding":{"unit":"px","top":"0","right":"0","bottom":"0","left":"0","isLinked":true},"content_width":"full","flex_justify_content":"flex-start","flex_align_items":"center","flex_gap_tablet":{"column":"30","row":"30","isLinked":true,"unit":"px","size":30},"animation":"fadeIn","animation_duration":"fast","animation_delay":750},"elements":[{"id":"6f6e54ba","settings":{"title":"WORKING WITH","header_size":"h5","title_color":"#FFFFFF","typography_typography":"custom","typography_font_family":"Manrope","typography_font_size":{"unit":"px","size":22,"sizes":[]},"typography_font_size_tablet":{"unit":"px","size":22,"sizes":[]},"typography_font_size_mobile":{"unit":"px","size":22,"sizes":[]},"typography_font_weight":"800","typography_line_height":{"unit":"em","size":1,"sizes":[]},"typography_letter_spacing":{"unit":"px","size":-0.4,"sizes":[]},"typography_letter_spacing_tablet":{"unit":"px","size":-0.4,"sizes":[]},"typography_letter_spacing_mobile":{"unit":"px","size":-0.4,"sizes":[]},"_margin":{"unit":"px","top":"-3","right":"0","bottom":"-3","left":"0","isLinked":false},"_margin_tablet":{"unit":"px","top":"-3","right":"0","bottom":"-3","left":"0","isLinked":false},"_margin_mobile":{"unit":"px","top":"-3","right":"0","bottom":"-3","left":"0","isLinked":false},"content_width":"full"},"elements":[],"isInner":false,"widgetType":"heading","elType":"widget"},{"id":"59231886","settings":{"text":"Divider","color":"#FFFFFF42","gap":{"unit":"px","size":0,"sizes":[]},"content_width":"full"},"elements":[],"isInner":false,"widgetType":"divider","elType":"widget"},{"id":"1419bb65","settings":{"container_type":"grid","presetTitle":"Grid","presetIcon":"eicon-container-grid","content_width":"full","grid_columns_grid":{"unit":"fr","size":6,"sizes":[]},"grid_columns_grid_mobile":{"unit":"fr","size":2,"sizes":[]},"grid_rows_grid":{"unit":"fr","size":1,"sizes":[]},"grid_gaps":{"column":"20","row":"20","isLinked":true,"unit":"px"},"grid_gaps_tablet":{"column":"20","row":"20","isLinked":true,"unit":"px"},"grid_justify_items":"center","grid_align_items":"center","padding":{"unit":"px","top":"0","right":"0","bottom":"0","left":"0","isLinked":true}},"elements":[{"id":"e260577","settings":{"content_width":"full","image":{"url":"https:\/\/preview.section.express\/wp-content\/uploads\/2024\/05\/logo-container-1.png","id":1420,"size":"","alt":"","source":"library"},"image_size":"custom","image_custom_dimension":{"width":"120","height":""},"align":"center"},"elements":[],"isInner":false,"widgetType":"image","elType":"widget"},{"id":"26873d4c","settings":{"content_width":"full","image":{"url":"https:\/\/preview.section.express\/wp-content\/uploads\/2024\/05\/logo-container-2.png","id":1421,"size":"","alt":"","source":"library"},"image_size":"custom","image_custom_dimension":{"width":"120","height":""},"align":"center"},"elements":[],"isInner":false,"widgetType":"image","elType":"widget"},{"id":"4a0f6060","settings":{"content_width":"full","image":{"url":"https:\/\/preview.section.express\/wp-content\/uploads\/2024\/05\/logo-container-3.png","id":1422,"size":"","alt":"","source":"library"},"image_size":"custom","image_custom_dimension":{"width":"120","height":""},"align":"center"},"elements":[],"isInner":false,"widgetType":"image","elType":"widget"},{"id":"528e274b","settings":{"content_width":"full","image":{"url":"https:\/\/preview.section.express\/wp-content\/uploads\/2024\/05\/logo-container-4.png","id":1423,"size":"","alt":"","source":"library"},"image_size":"custom","image_custom_dimension":{"width":"120","height":""},"align":"center"},"elements":[],"isInner":false,"widgetType":"image","elType":"widget"},{"id":"c09800","settings":{"content_width":"full","image":{"url":"https:\/\/preview.section.express\/wp-content\/uploads\/2024\/05\/logo-container-5.png","id":1424,"size":"","alt":"","source":"library"},"image_size":"custom","image_custom_dimension":{"width":"120","height":""},"align":"center"},"elements":[],"isInner":false,"widgetType":"image","elType":"widget"},{"id":"2847f033","settings":{"content_width":"full","image":{"url":"https:\/\/preview.section.express\/wp-content\/uploads\/2024\/05\/logo-container-6.png","id":1425,"size":"","alt":"","source":"library"},"image_size":"custom","image_custom_dimension":{"width":"120","height":""},"align":"center"},"elements":[],"isInner":false,"widgetType":"image","elType":"widget"}],"isInner":true,"elType":"container"}],"isInner":true,"elType":"container"}],"isInner":true,"elType":"container"}],"isInner":true,"elType":"container","isLocked":true}],"isInner":false,"widgetType":"nested-carousel","elType":"widget"}],"isInner":false,"elType":"container"}],"page_settings":[],"version":"0.4","title":"c2557","type":"container"}