{"content":[{"id":"7fcfa951","settings":{"flex_direction":"column","boxed_width":{"unit":"px","size":1290,"sizes":[]},"flex_gap":{"column":"0","row":"0","isLinked":true,"unit":"px","size":0},"background_background":"classic","background_color":"#F5F5F5","padding":{"unit":"px","top":"120","right":"40","bottom":"120","left":"40","isLinked":false},"padding_tablet":{"unit":"px","top":"80","right":"40","bottom":"80","left":"40","isLinked":false},"padding_mobile":{"unit":"px","top":"60","right":"20","bottom":"60","left":"20","isLinked":false},"_title":"c1705"},"elements":[{"id":"47549476","settings":{"boxed_width":{"unit":"px","size":1290,"sizes":[]},"flex_direction":"row","flex_gap":{"column":"0","row":"0","isLinked":true,"unit":"px","size":0},"background_color":"#ECC5C5","padding":{"unit":"px","top":"0","right":"0","bottom":"0","left":"0","isLinked":true},"container_type":"grid","grid_columns_grid":{"unit":"custom","size":"1fr 2fr","sizes":[]},"grid_columns_grid_tablet":{"unit":"fr","size":1,"sizes":[]},"grid_rows_grid":{"unit":"fr","size":1,"sizes":[]},"grid_gaps":{"column":"0","row":"0","isLinked":true,"unit":"px"},"presetTitle":"Grid","presetIcon":"eicon-container-grid"},"elements":[{"id":"501636ce","settings":{"content_width":"full","flex_direction":"column","flex_justify_content":"flex-start","flex_gap":{"column":"35","row":"35","isLinked":true,"unit":"px","size":35},"flex_gap_tablet":{"column":"30","row":"30","isLinked":true,"unit":"px","size":30},"padding":{"unit":"px","top":"0","right":"0","bottom":"0","left":"0","isLinked":true},"animation":"fadeIn","animation_duration":"fast","animation_delay":500},"elements":[{"id":"35a211b0","settings":{"title":"Sample Subtitle","header_size":"p","title_color":"#9F9F9F","typography_typography":"custom","typography_font_family":"Manrope","typography_font_size":{"unit":"px","size":13,"sizes":[]},"typography_font_weight":"600","typography_text_transform":"uppercase","typography_line_height":{"unit":"em","size":1,"sizes":[]},"_margin":{"unit":"px","top":"0","right":"0","bottom":"-4","left":"0","isLinked":false},"_margin_tablet":{"unit":"px","top":"0","right":"0","bottom":"-4","left":"0","isLinked":false},"content_width":"full"},"elements":[],"isInner":false,"widgetType":"heading","elType":"widget"},{"id":"32291501","settings":{"title":"New Awards","header_size":"h1","title_color":"#000000","typography_typography":"custom","typography_font_family":"Manrope","typography_font_size":{"unit":"px","size":52,"sizes":[]},"typography_font_size_tablet":{"unit":"px","size":42,"sizes":[]},"typography_font_size_mobile":{"unit":"px","size":38,"sizes":[]},"typography_font_weight":"800","typography_line_height":{"unit":"em","size":1,"sizes":[]},"typography_letter_spacing":{"unit":"px","size":-2,"sizes":[]},"typography_letter_spacing_tablet":{"unit":"px","size":-1.2,"sizes":[]},"_margin":{"unit":"px","top":"-7","right":"0","bottom":"-7","left":"0","isLinked":false},"_margin_tablet":{"unit":"px","top":"-7","right":"0","bottom":"-5","left":"0","isLinked":false},"_margin_mobile":{"unit":"px","top":"-6","right":"0","bottom":"-4","left":"0","isLinked":false},"content_width":"full"},"elements":[],"isInner":false,"widgetType":"heading","elType":"widget"}],"isInner":true,"elType":"container"},{"id":"acd818f","settings":{"content_width":"full","flex_direction":"column","flex_justify_content":"flex-start","flex_gap":{"column":"50","row":"50","isLinked":true,"unit":"px","size":50},"padding":{"unit":"px","top":"0","right":"0","bottom":"0","left":"0","isLinked":true},"animation":"fadeIn","animation_duration":"fast","animation_delay":750},"elements":[{"id":"5b894a9c","settings":{"content_width":"full","container_type":"grid","grid_columns_grid":{"unit":"custom","size":"3fr 1fr","sizes":[]},"grid_columns_grid_tablet":{"unit":"fr","size":1,"sizes":[]},"grid_rows_grid":{"unit":"fr","size":1,"sizes":[]},"grid_gaps":{"column":"50","row":"50","isLinked":true,"unit":"px"},"grid_gaps_tablet":{"column":"30","row":"30","isLinked":true,"unit":"px"},"grid_align_items":"start","padding":{"unit":"px","top":"46","right":"0","bottom":"0","left":"0","isLinked":false},"padding_tablet":{"unit":"px","top":"30","right":"0","bottom":"0","left":"0","isLinked":false},"presetTitle":"Grid","presetIcon":"eicon-container-grid"},"elements":[{"id":"2a7d6a43","settings":{"editor":"<p>Sed unde omnis iste natus sit volur tatem accus antium laudan tium totam rem aperiam eaque ipsa ab illo inventore veritatis exceur sante monaca\u00a0 architecto beatae vitae dicta sunt explicabo.<\/p>","text_color":"#9F9F9F","typography_typography":"custom","typography_font_family":"Manrope","typography_font_size":{"unit":"px","size":17,"sizes":[]},"typography_font_weight":"500","typography_line_height":{"unit":"em","size":1.6,"sizes":[]},"_margin":{"unit":"px","top":"-7","right":"0","bottom":"-21","left":"0","isLinked":false},"_element_width_tablet":"initial","_element_width_mobile":"inherit","_element_custom_width_tablet":{"unit":"px","size":599,"sizes":[]},"content_width":"full"},"elements":[],"isInner":false,"widgetType":"text-editor","elType":"widget"},{"id":"7cf7692c","settings":{"text":"Learn More","selected_icon":{"value":"fas fa-arrow-right","library":"fa-solid"},"icon_align":"right","icon_indent":{"unit":"px","size":5,"sizes":[]},"typography_typography":"custom","typography_font_family":"Manrope","typography_font_size":{"unit":"px","size":15,"sizes":[]},"typography_font_weight":"800","typography_line_height":{"unit":"em","size":1,"sizes":[]},"button_text_color":"#000000","background_color":"#00000000","hover_color":"#686868","button_background_hover_color":"#00000000","button_hover_border_color":"#000000","border_border":"none","border_width":{"unit":"px","top":"1","right":"1","bottom":"1","left":"1","isLinked":true},"border_color":"#000000","border_radius":{"unit":"px","top":"0","right":"0","bottom":"0","left":"0","isLinked":true},"text_padding":{"unit":"px","top":"0","right":"0","bottom":"0","left":"0","isLinked":true},"_margin":{"unit":"px","top":"-7","right":"0","bottom":"-6","left":"0","isLinked":false},"typography_text_transform":"uppercase","align":"right","align_tablet":"left","content_width":"full"},"elements":[],"isInner":false,"widgetType":"button","elType":"widget"}],"isInner":true,"elType":"container"},{"id":"2cfa14ee","settings":{"text":"Divider","color":"#D8D8D8","gap":{"unit":"px","size":0,"sizes":[]},"content_width":"full"},"elements":[],"isInner":false,"widgetType":"divider","elType":"widget"},{"id":"6b03cd13","settings":{"content_width":"full","container_type":"grid","grid_columns_grid":{"unit":"fr","size":2,"sizes":[]},"grid_columns_grid_tablet":{"unit":"fr","size":1,"sizes":[]},"grid_rows_grid":{"unit":"fr","size":1,"sizes":[]},"grid_gaps":{"column":"50","row":"60","isLinked":false,"unit":"px"},"grid_gaps_tablet":{"column":"50","row":"50","isLinked":true,"unit":"px"},"grid_gaps_mobile":{"column":"0","row":"50","isLinked":false,"unit":"px"},"padding":{"unit":"px","top":"0","right":"0","bottom":"0","left":"0","isLinked":true},"presetTitle":"Grid","presetIcon":"eicon-container-grid"},"elements":[{"id":"58028f23","settings":{"content_width":"full","flex_direction":"column","flex_justify_content":"flex-start","flex_align_items":"flex-start","flex_gap":{"column":"30","row":"30","isLinked":true,"unit":"px","size":30},"padding":{"unit":"px","top":"0","right":"0","bottom":"0","left":"0","isLinked":true}},"elements":[{"id":"1ca11961","settings":{"price_list":[{"title":"E-Commerce Integration","price":"2015","link":{"url":""},"_id":"1039099"}],"heading_color":"#000000","heading_typography_typography":"custom","heading_typography_font_family":"Manrope","heading_typography_font_size":{"unit":"px","size":22,"sizes":[]},"heading_typography_font_weight":"900","heading_typography_line_height":{"unit":"em","size":1,"sizes":[]},"heading_typography_letter_spacing":{"unit":"px","size":-0.4,"sizes":[]},"price_color":"#9F9F9F","price_typography_typography":"custom","price_typography_font_family":"Manrope","price_typography_font_size":{"unit":"px","size":22,"sizes":[]},"price_typography_font_weight":"400","price_typography_line_height":{"unit":"em","size":1,"sizes":[]},"price_typography_letter_spacing":{"unit":"px","size":-0.4,"sizes":[]},"description_color":"#9F9F9F","description_typography_typography":"custom","description_typography_font_family":"Manrope","description_typography_font_size":{"unit":"px","size":15,"sizes":[]},"description_typography_font_weight":"500","description_typography_line_height":{"unit":"em","size":2,"sizes":[]},"description_typography_line_height_tablet":{"unit":"em","size":1.6,"sizes":[]},"separator_style":"none","separator_weight":{"unit":"px","size":1,"sizes":[]},"separator_color":"#D8D8D8","separator_spacing":{"unit":"px","size":20,"sizes":[]},"row_gap":{"unit":"px","size":25,"sizes":[]},"_margin":{"unit":"px","top":"-3","right":"0","bottom":"-13","left":"0","isLinked":false},"animation_duration":"fast","_animation_delay":750,"content_width":"full"},"elements":[],"isInner":false,"widgetType":"price-list","elType":"widget"},{"id":"8edad75","settings":{"title":"Sample Subtitle","header_size":"p","title_color":"#9F9F9F","typography_typography":"custom","typography_font_family":"Manrope","typography_font_size":{"unit":"px","size":13,"sizes":[]},"typography_font_weight":"600","typography_text_transform":"uppercase","typography_line_height":{"unit":"em","size":1,"sizes":[]},"_margin":{"unit":"px","top":"0","right":"0","bottom":"-4","left":"0","isLinked":false},"_margin_tablet":{"unit":"px","top":"0","right":"0","bottom":"-4","left":"0","isLinked":false},"content_width":"full"},"elements":[],"isInner":false,"widgetType":"heading","elType":"widget"},{"id":"4268f064","settings":{"editor":"<p>Accus antium laudan tium totam rem aperiam eaque ipsa ab illo inventore veritatis et architecto.<\/p>","text_color":"#9F9F9F","typography_typography":"custom","typography_font_family":"Manrope","typography_font_size":{"unit":"px","size":15,"sizes":[]},"typography_font_weight":"500","typography_line_height":{"unit":"em","size":1.6,"sizes":[]},"_margin":{"unit":"px","top":"-5","right":"0","bottom":"-20","left":"0","isLinked":false},"_element_width_tablet":"initial","_element_width_mobile":"inherit","_element_custom_width_tablet":{"unit":"px","size":453,"sizes":[]},"content_width":"full"},"elements":[],"isInner":false,"widgetType":"text-editor","elType":"widget"}],"isInner":true,"elType":"container"},{"id":"5a75851c","settings":{"content_width":"full","flex_direction":"column","flex_justify_content":"flex-start","flex_align_items":"flex-start","flex_gap":{"column":"30","row":"30","isLinked":true,"unit":"px","size":30},"padding":{"unit":"px","top":"0","right":"0","bottom":"0","left":"0","isLinked":true}},"elements":[{"id":"3fa3187d","settings":{"price_list":[{"title":"SEO Strategy Consulting","price":"2012","link":{"url":""},"_id":"1039099"}],"heading_color":"#000000","heading_typography_typography":"custom","heading_typography_font_family":"Manrope","heading_typography_font_size":{"unit":"px","size":22,"sizes":[]},"heading_typography_font_weight":"900","heading_typography_line_height":{"unit":"em","size":1,"sizes":[]},"heading_typography_letter_spacing":{"unit":"px","size":-0.4,"sizes":[]},"price_color":"#9F9F9F","price_typography_typography":"custom","price_typography_font_family":"Manrope","price_typography_font_size":{"unit":"px","size":22,"sizes":[]},"price_typography_font_weight":"400","price_typography_line_height":{"unit":"em","size":1,"sizes":[]},"price_typography_letter_spacing":{"unit":"px","size":-0.4,"sizes":[]},"description_color":"#9F9F9F","description_typography_typography":"custom","description_typography_font_family":"Manrope","description_typography_font_size":{"unit":"px","size":15,"sizes":[]},"description_typography_font_weight":"500","description_typography_line_height":{"unit":"em","size":2,"sizes":[]},"description_typography_line_height_tablet":{"unit":"em","size":1.6,"sizes":[]},"separator_style":"none","separator_weight":{"unit":"px","size":1,"sizes":[]},"separator_color":"#D8D8D8","separator_spacing":{"unit":"px","size":20,"sizes":[]},"row_gap":{"unit":"px","size":25,"sizes":[]},"_margin":{"unit":"px","top":"-3","right":"0","bottom":"-13","left":"0","isLinked":false},"animation_duration":"fast","_animation_delay":750,"content_width":"full"},"elements":[],"isInner":false,"widgetType":"price-list","elType":"widget"},{"id":"5956ebd7","settings":{"title":"Sample Subtitle","header_size":"p","title_color":"#9F9F9F","typography_typography":"custom","typography_font_family":"Manrope","typography_font_size":{"unit":"px","size":13,"sizes":[]},"typography_font_weight":"600","typography_text_transform":"uppercase","typography_line_height":{"unit":"em","size":1,"sizes":[]},"_margin":{"unit":"px","top":"0","right":"0","bottom":"-4","left":"0","isLinked":false},"_margin_tablet":{"unit":"px","top":"0","right":"0","bottom":"-4","left":"0","isLinked":false},"content_width":"full"},"elements":[],"isInner":false,"widgetType":"heading","elType":"widget"},{"id":"377f8d28","settings":{"editor":"<p>Accus antium laudan tium totam rem aperiam eaque ipsa ab illo inventore veritatis et architecto.<\/p>","text_color":"#9F9F9F","typography_typography":"custom","typography_font_family":"Manrope","typography_font_size":{"unit":"px","size":15,"sizes":[]},"typography_font_weight":"500","typography_line_height":{"unit":"em","size":1.6,"sizes":[]},"_margin":{"unit":"px","top":"-5","right":"0","bottom":"-20","left":"0","isLinked":false},"_element_width_tablet":"initial","_element_width_mobile":"inherit","_element_custom_width_tablet":{"unit":"px","size":453,"sizes":[]},"content_width":"full"},"elements":[],"isInner":false,"widgetType":"text-editor","elType":"widget"}],"isInner":true,"elType":"container"},{"id":"77383891","settings":{"content_width":"full","flex_direction":"column","flex_justify_content":"flex-start","flex_align_items":"flex-start","flex_gap":{"column":"30","row":"30","isLinked":true,"unit":"px","size":30},"padding":{"unit":"px","top":"0","right":"0","bottom":"0","left":"0","isLinked":true}},"elements":[{"id":"255389dd","settings":{"price_list":[{"title":"Cloud Hosting Services","price":"2021","link":{"url":""},"_id":"1039099"}],"heading_color":"#000000","heading_typography_typography":"custom","heading_typography_font_family":"Manrope","heading_typography_font_size":{"unit":"px","size":22,"sizes":[]},"heading_typography_font_weight":"900","heading_typography_line_height":{"unit":"em","size":1,"sizes":[]},"heading_typography_letter_spacing":{"unit":"px","size":-0.4,"sizes":[]},"price_color":"#9F9F9F","price_typography_typography":"custom","price_typography_font_family":"Manrope","price_typography_font_size":{"unit":"px","size":22,"sizes":[]},"price_typography_font_weight":"400","price_typography_line_height":{"unit":"em","size":1,"sizes":[]},"price_typography_letter_spacing":{"unit":"px","size":-0.4,"sizes":[]},"description_color":"#9F9F9F","description_typography_typography":"custom","description_typography_font_family":"Manrope","description_typography_font_size":{"unit":"px","size":15,"sizes":[]},"description_typography_font_weight":"500","description_typography_line_height":{"unit":"em","size":2,"sizes":[]},"description_typography_line_height_tablet":{"unit":"em","size":1.6,"sizes":[]},"separator_style":"none","separator_weight":{"unit":"px","size":1,"sizes":[]},"separator_color":"#D8D8D8","separator_spacing":{"unit":"px","size":20,"sizes":[]},"row_gap":{"unit":"px","size":25,"sizes":[]},"_margin":{"unit":"px","top":"-3","right":"0","bottom":"-13","left":"0","isLinked":false},"animation_duration":"fast","_animation_delay":750,"content_width":"full"},"elements":[],"isInner":false,"widgetType":"price-list","elType":"widget"},{"id":"3947d87a","settings":{"title":"Sample Subtitle","header_size":"p","title_color":"#9F9F9F","typography_typography":"custom","typography_font_family":"Manrope","typography_font_size":{"unit":"px","size":13,"sizes":[]},"typography_font_weight":"600","typography_text_transform":"uppercase","typography_line_height":{"unit":"em","size":1,"sizes":[]},"_margin":{"unit":"px","top":"0","right":"0","bottom":"-4","left":"0","isLinked":false},"_margin_tablet":{"unit":"px","top":"0","right":"0","bottom":"-4","left":"0","isLinked":false},"content_width":"full"},"elements":[],"isInner":false,"widgetType":"heading","elType":"widget"},{"id":"45078a56","settings":{"editor":"<p>Accus antium laudan tium totam rem aperiam eaque ipsa ab illo inventore veritatis et architecto.<\/p>","text_color":"#9F9F9F","typography_typography":"custom","typography_font_family":"Manrope","typography_font_size":{"unit":"px","size":15,"sizes":[]},"typography_font_weight":"500","typography_line_height":{"unit":"em","size":1.6,"sizes":[]},"_margin":{"unit":"px","top":"-5","right":"0","bottom":"-20","left":"0","isLinked":false},"_element_width_tablet":"initial","_element_width_mobile":"inherit","_element_custom_width_tablet":{"unit":"px","size":453,"sizes":[]},"content_width":"full"},"elements":[],"isInner":false,"widgetType":"text-editor","elType":"widget"}],"isInner":true,"elType":"container"},{"id":"30f24782","settings":{"content_width":"full","flex_direction":"column","flex_justify_content":"flex-start","flex_align_items":"flex-start","flex_gap":{"column":"30","row":"30","isLinked":true,"unit":"px","size":30},"padding":{"unit":"px","top":"0","right":"0","bottom":"0","left":"0","isLinked":true}},"elements":[{"id":"56145c65","settings":{"price_list":[{"title":"Mobile App Development","price":"2024","link":{"url":""},"_id":"1039099"}],"heading_color":"#000000","heading_typography_typography":"custom","heading_typography_font_family":"Manrope","heading_typography_font_size":{"unit":"px","size":22,"sizes":[]},"heading_typography_font_weight":"900","heading_typography_line_height":{"unit":"em","size":1,"sizes":[]},"heading_typography_letter_spacing":{"unit":"px","size":-0.4,"sizes":[]},"price_color":"#9F9F9F","price_typography_typography":"custom","price_typography_font_family":"Manrope","price_typography_font_size":{"unit":"px","size":22,"sizes":[]},"price_typography_font_weight":"400","price_typography_line_height":{"unit":"em","size":1,"sizes":[]},"price_typography_letter_spacing":{"unit":"px","size":-0.4,"sizes":[]},"description_color":"#9F9F9F","description_typography_typography":"custom","description_typography_font_family":"Manrope","description_typography_font_size":{"unit":"px","size":15,"sizes":[]},"description_typography_font_weight":"500","description_typography_line_height":{"unit":"em","size":2,"sizes":[]},"description_typography_line_height_tablet":{"unit":"em","size":1.6,"sizes":[]},"separator_style":"none","separator_weight":{"unit":"px","size":1,"sizes":[]},"separator_color":"#D8D8D8","separator_spacing":{"unit":"px","size":20,"sizes":[]},"row_gap":{"unit":"px","size":25,"sizes":[]},"_margin":{"unit":"px","top":"-3","right":"0","bottom":"-13","left":"0","isLinked":false},"animation_duration":"fast","_animation_delay":750,"content_width":"full"},"elements":[],"isInner":false,"widgetType":"price-list","elType":"widget"},{"id":"6f91ccf4","settings":{"title":"Sample Subtitle","header_size":"p","title_color":"#9F9F9F","typography_typography":"custom","typography_font_family":"Manrope","typography_font_size":{"unit":"px","size":13,"sizes":[]},"typography_font_weight":"600","typography_text_transform":"uppercase","typography_line_height":{"unit":"em","size":1,"sizes":[]},"_margin":{"unit":"px","top":"0","right":"0","bottom":"-4","left":"0","isLinked":false},"_margin_tablet":{"unit":"px","top":"0","right":"0","bottom":"-4","left":"0","isLinked":false},"content_width":"full"},"elements":[],"isInner":false,"widgetType":"heading","elType":"widget"},{"id":"3b416516","settings":{"editor":"<p>Accus antium laudan tium totam rem aperiam eaque ipsa ab illo inventore veritatis et architecto.<\/p>","text_color":"#9F9F9F","typography_typography":"custom","typography_font_family":"Manrope","typography_font_size":{"unit":"px","size":15,"sizes":[]},"typography_font_weight":"500","typography_line_height":{"unit":"em","size":1.6,"sizes":[]},"_margin":{"unit":"px","top":"-5","right":"0","bottom":"-20","left":"0","isLinked":false},"_element_width_tablet":"initial","_element_width_mobile":"inherit","_element_custom_width_tablet":{"unit":"px","size":453,"sizes":[]},"content_width":"full"},"elements":[],"isInner":false,"widgetType":"text-editor","elType":"widget"}],"isInner":true,"elType":"container"}],"isInner":true,"elType":"container"}],"isInner":true,"elType":"container"}],"isInner":true,"elType":"container"}],"isInner":false,"elType":"container"}],"page_settings":[],"version":"0.4","title":"c1705","type":"container"}