{"content":[{"id":"6f923ccd","settings":{"flex_direction":"column","boxed_width":{"unit":"px","size":1290,"sizes":[]},"flex_gap":{"column":"0","row":"0","isLinked":true,"unit":"px","size":0},"background_background":"classic","background_color":"#F5F5F5","padding":{"unit":"px","top":"0","right":"0","bottom":"0","left":"0","isLinked":false},"padding_tablet":{"unit":"px","top":"0","right":"0","bottom":"0","left":"0","isLinked":false},"padding_mobile":{"unit":"px","top":"0","right":"0","bottom":"0","left":"0","isLinked":false},"_title":"c2335","content_width":"full","flex_gap_tablet":{"column":"0","row":"0","isLinked":true,"unit":"px","size":0}},"elements":[{"id":"4e9520a0","settings":{"content_width":"full","min_height":{"unit":"vh","size":100,"sizes":[]},"min_height_tablet":{"unit":"vh","size":50,"sizes":[]},"min_height_mobile":{"unit":"vh","size":"","sizes":[]},"flex_direction":"column","flex_justify_content":"center","flex_align_items":"center","flex_gap":{"column":"0","row":"0","isLinked":true,"unit":"px","size":0},"background_position":"center center","background_repeat":"no-repeat","background_size":"cover","padding":{"unit":"px","top":"0","right":"0","bottom":"0","left":"0","isLinked":true},"__dynamic__":{"background_image":"[elementor-tag id=\"7e5ff96\" name=\"post-featured-image\" settings=\"%7B%7D\"]"},"background_background":"classic"},"elements":[{"id":"219128c1","settings":{"content_width":"full"},"elements":[],"isInner":false,"widgetType":"spacer","elType":"widget"}],"isInner":true,"elType":"container"},{"id":"5c650dcd","settings":{"boxed_width":{"unit":"px","size":1290,"sizes":[]},"flex_direction":"column","flex_gap":{"column":"50","row":"50","isLinked":true,"unit":"px","size":50},"padding":{"unit":"px","top":"0","right":"40","bottom":"0","left":"40","isLinked":false},"padding_mobile":{"unit":"px","top":"0","right":"20","bottom":"0","left":"20","isLinked":false},"flex_justify_content":"flex-start","flex_align_items":"center","flex_gap_tablet":{"column":"50","row":"50","isLinked":true,"unit":"px","size":50},"background_position":"center center","background_repeat":"no-repeat","background_size":"cover","padding_tablet":{"unit":"px","top":"0","right":"40","bottom":"0","left":"40","isLinked":false},"__dynamic__":{"background_image":"[elementor-tag id=\"0b708df\" name=\"post-featured-image\" settings=\"%7B%7D\"]"},"background_color":"#02010100","background_image":{"url":"","id":"","size":"","alt":"","source":"library"}},"elements":[{"id":"1e38cbbd","settings":{"content_width":"full","boxed_width":{"unit":"px","size":1290,"sizes":[]},"flex_direction":"column","flex_justify_content":"flex-start","flex_gap":{"column":"50","row":"50","isLinked":true,"unit":"px","size":50},"background_background":"classic","background_color":"#F5F5F5","margin":{"unit":"custom","top":"-30vh","right":"0","bottom":"0","left":"0","isLinked":false},"margin_tablet":{"unit":"px","top":"-100","right":"0","bottom":"0","left":"0","isLinked":false},"padding":{"unit":"px","top":"100","right":"100","bottom":"100","left":"100","isLinked":true},"padding_tablet":{"unit":"px","top":"70","right":"70","bottom":"70","left":"70","isLinked":true},"padding_mobile":{"unit":"px","top":"50","right":"30","bottom":"50","left":"30","isLinked":false},"z_index":2},"elements":[{"id":"1f747728","settings":{"flex_direction":"column","flex_justify_content":"flex-start","flex_align_items":"center","flex_gap":{"column":"40","row":"40","isLinked":true,"unit":"px","size":40},"flex_gap_tablet":{"column":"35","row":"35","isLinked":true,"unit":"px","size":35},"padding":{"unit":"px","top":"0","right":"0","bottom":"0","left":"0","isLinked":true},"boxed_width":{"unit":"px","size":1000,"sizes":[]},"content_width":"full"},"elements":[{"id":"35eb7807","settings":{"content_width":"full","icon_list":[{"_id":"ba942ce","custom_date_format":"M d \u2014 Y","custom_time_format":"g:i a","show_icon":"none","date_format":"custom","type":"terms","taxonomy":"category"}],"space_between":{"unit":"px","size":28,"sizes":[]},"icon_align":"left","icon_color":"#FFFFFF","icon_size":{"unit":"px","size":22,"sizes":[]},"text_indent":{"unit":"px","size":0,"sizes":[]},"text_color":"#FFFFFF","icon_typography_typography":"custom","icon_typography_font_family":"Manrope","icon_typography_font_size":{"unit":"px","size":14,"sizes":[]},"icon_typography_font_weight":"500","icon_typography_line_height":{"unit":"em","size":1,"sizes":[]},"_margin":{"unit":"px","top":"0","right":"0","bottom":"0","left":"0","isLinked":false},"divider":"yes","divider_height":{"unit":"px","size":"","sizes":[]},"divider_color":"#6B6B6B","_padding":{"unit":"px","top":"14","right":"20","bottom":"14","left":"20","isLinked":false},"_background_background":"classic","_background_color":"#000000","_border_radius":{"unit":"px","top":"100","right":"100","bottom":"100","left":"100","isLinked":true},"icon_typography_text_transform":"uppercase","_background_color_stop_tablet":{"unit":"%","size":"","sizes":[]},"_background_color_stop_mobile":{"unit":"%","size":"","sizes":[]},"_background_color_b_stop_tablet":{"unit":"%","size":"","sizes":[]},"_background_color_b_stop_mobile":{"unit":"%","size":"","sizes":[]},"_background_gradient_angle_tablet":{"unit":"deg","size":"","sizes":[]},"_background_gradient_angle_mobile":{"unit":"deg","size":"","sizes":[]},"_background_hover_color_stop_tablet":{"unit":"%","size":"","sizes":[]},"_background_hover_color_stop_mobile":{"unit":"%","size":"","sizes":[]},"_background_hover_color_b_stop_tablet":{"unit":"%","size":"","sizes":[]},"_background_hover_color_b_stop_mobile":{"unit":"%","size":"","sizes":[]},"_background_hover_gradient_angle_tablet":{"unit":"deg","size":"","sizes":[]},"_background_hover_gradient_angle_mobile":{"unit":"deg","size":"","sizes":[]}},"elements":[],"isInner":false,"widgetType":"post-info","elType":"widget"},{"id":"38a29571","settings":{"content_width":"full","__dynamic__":{"title":"[elementor-tag id=\"\" name=\"post-title\" settings=\"%7B%22before%22%3A%22%22%2C%22after%22%3A%22%22%2C%22fallback%22%3A%22%22%7D\"]"},"title":"Add Your Heading Text Here","align":"center","title_color":"#000000","typography_typography":"custom","typography_font_family":"Manrope","typography_font_size":{"unit":"px","size":52,"sizes":[]},"typography_font_size_tablet":{"unit":"px","size":42,"sizes":[]},"typography_font_size_mobile":{"unit":"px","size":38,"sizes":[]},"typography_font_weight":"900","typography_line_height":{"unit":"em","size":1.1,"sizes":[]},"typography_letter_spacing":{"unit":"px","size":-2,"sizes":[]},"typography_letter_spacing_tablet":{"unit":"px","size":-1.2,"sizes":[]},"_margin":{"unit":"px","top":"-10","right":"0","bottom":"-9","left":"0","isLinked":false},"_margin_tablet":{"unit":"px","top":"-9","right":"0","bottom":"-7","left":"0","isLinked":false},"_margin_mobile":{"unit":"px","top":"-7","right":"0","bottom":"-7","left":"0","isLinked":false},"_element_width":"initial","_element_width_tablet":"inherit","_element_width_mobile":"inherit","_element_custom_width":{"unit":"px","size":561,"sizes":[]},"_element_custom_width_tablet":{"unit":"px","size":522,"sizes":[]}},"elements":[],"isInner":false,"widgetType":"theme-post-title","elType":"widget"},{"id":"2ab08bee","settings":{"content_width":"full","icon_list":[{"selected_icon":{"value":{"url":"https:\/\/preview.section.express\/wp-content\/uploads\/2024\/07\/blog-icon-list-3.svg","id":22633},"library":"svg"},"_id":"ba942ce","custom_date_format":"M d \u2014 Y","custom_time_format":"g:i a","link":"","show_icon":"none","date_format":"custom"},{"selected_icon":{"value":{"url":"https:\/\/preview.section.express\/wp-content\/uploads\/2024\/07\/blog-icon-list-3.svg","id":22633},"library":"svg"},"custom_date_format":"F j, Y","custom_time_format":"g:i a","show_icon":"none","type":"author","_id":"22ca965","text_prefix":"By"},{"selected_icon":{"value":{"url":"https:\/\/preview.section.express\/wp-content\/uploads\/2024\/07\/blog-icon-list-3.svg","id":22633},"library":"svg"},"custom_date_format":"F j, Y","custom_time_format":"g:i a","show_icon":"none","type":"comments","comments_custom_strings":"yes","link":"","_id":"1f73ce6"}],"space_between":{"unit":"px","size":22,"sizes":[]},"icon_align":"left","icon_color":"#000000","icon_size":{"unit":"px","size":22,"sizes":[]},"text_indent":{"unit":"px","size":0,"sizes":[]},"text_color":"#9F9F9F","icon_typography_typography":"custom","icon_typography_font_family":"Manrope","icon_typography_font_size":{"unit":"px","size":14,"sizes":[]},"icon_typography_font_weight":"500","icon_typography_line_height":{"unit":"em","size":1,"sizes":[]},"_margin":{"unit":"px","top":"-2","right":"0","bottom":"-2","left":"0","isLinked":false},"divider":"yes","divider_height":{"unit":"px","size":"","sizes":[]},"divider_color":"#D8D8D8","_background_color_stop_tablet":{"unit":"%","size":"","sizes":[]},"_background_color_stop_mobile":{"unit":"%","size":"","sizes":[]},"_background_color_b_stop_tablet":{"unit":"%","size":"","sizes":[]},"_background_color_b_stop_mobile":{"unit":"%","size":"","sizes":[]},"_background_gradient_angle_tablet":{"unit":"deg","size":"","sizes":[]},"_background_gradient_angle_mobile":{"unit":"deg","size":"","sizes":[]},"_background_hover_color_stop_tablet":{"unit":"%","size":"","sizes":[]},"_background_hover_color_stop_mobile":{"unit":"%","size":"","sizes":[]},"_background_hover_color_b_stop_tablet":{"unit":"%","size":"","sizes":[]},"_background_hover_color_b_stop_mobile":{"unit":"%","size":"","sizes":[]},"_background_hover_gradient_angle_tablet":{"unit":"deg","size":"","sizes":[]},"_background_hover_gradient_angle_mobile":{"unit":"deg","size":"","sizes":[]},"icon_typography_line_height_mobile":{"unit":"em","size":1.6,"sizes":[]},"_margin_mobile":{"unit":"px","top":"-6","right":"0","bottom":"-6","left":"0","isLinked":false}},"elements":[],"isInner":false,"widgetType":"post-info","elType":"widget"}],"isInner":true,"elType":"container"},{"id":"5bbf09e6","settings":{"flex_direction":"column","flex_justify_content":"flex-start","flex_align_items":"flex-start","flex_gap":{"column":"0","row":"0","isLinked":true,"unit":"px","size":0},"flex_gap_tablet":{"column":"0","row":"0","isLinked":true,"unit":"px","size":0},"padding":{"unit":"px","top":"20","right":"0","bottom":"20","left":"0","isLinked":false},"boxed_width":{"unit":"px","size":1000,"sizes":[]},"padding_tablet":{"unit":"px","top":"0","right":"0","bottom":"0","left":"0","isLinked":false},"content_width":"full"},"elements":[{"id":"2a0e3482","settings":{"content_width":"full","align":"left","text_color":"#9F9F9F","typography_typography":"custom","typography_font_family":"Manrope","typography_font_size":{"unit":"px","size":15,"sizes":[]},"typography_font_weight":"500","typography_line_height":{"unit":"em","size":1.6,"sizes":[]},"_margin":{"unit":"px","top":"-6","right":"0","bottom":"-22","left":"0","isLinked":false}},"elements":[],"isInner":false,"widgetType":"theme-post-content","elType":"widget"}],"isInner":true,"elType":"container"},{"id":"45646066","settings":{"content_width":"full","container_type":"grid","flex_direction":"row","flex_justify_content":"space-between","flex_align_items":"center","flex_gap":{"column":"30","row":"30","isLinked":true,"unit":"px","size":30},"flex_gap_tablet":{"column":"30","row":"30","isLinked":true,"unit":"px","size":30},"grid_columns_grid":{"unit":"fr","size":2,"sizes":[]},"grid_columns_grid_tablet":{"unit":"fr","size":1,"sizes":[]},"grid_rows_grid":{"unit":"fr","size":1,"sizes":[]},"grid_gaps":{"column":"30","row":"30","isLinked":true,"unit":"px"},"grid_align_items":"center","padding":{"unit":"px","top":"30","right":"0","bottom":"30","left":"0","isLinked":false},"presetTitle":"Grid","presetIcon":"eicon-container-grid","boxed_width":{"unit":"px","size":1000,"sizes":[]},"border_border":"solid","border_width":{"unit":"px","top":"1","right":"0","bottom":"1","left":"0","isLinked":false},"border_color":"#D8D8D8"},"elements":[{"id":"2fc8387f","settings":{"content_width":"full","icon_list":[{"selected_icon":{"value":{"url":"https:\/\/preview.section.express\/wp-content\/uploads\/2024\/07\/blog-icon-list-3.svg","id":22633},"library":"svg"},"_id":"ba942ce","custom_date_format":"M d \u2014 Y","custom_time_format":"g:i a","show_icon":"none","date_format":"custom","type":"terms","taxonomy":"post_tag"}],"space_between":{"unit":"px","size":20,"sizes":[]},"icon_align":"left","icon_color":"#000000","icon_size":{"unit":"px","size":22,"sizes":[]},"text_indent":{"unit":"px","size":0,"sizes":[]},"text_color":"#000000","icon_typography_typography":"custom","icon_typography_font_family":"Manrope","icon_typography_font_size":{"unit":"px","size":14,"sizes":[]},"icon_typography_font_weight":"600","icon_typography_line_height":{"unit":"em","size":1,"sizes":[]},"_margin":{"unit":"px","top":"-2","right":"0","bottom":"-2","left":"0","isLinked":false},"_background_color_stop_tablet":{"unit":"%","size":"","sizes":[]},"_background_color_stop_mobile":{"unit":"%","size":"","sizes":[]},"_background_color_b_stop_tablet":{"unit":"%","size":"","sizes":[]},"_background_color_b_stop_mobile":{"unit":"%","size":"","sizes":[]},"_background_gradient_angle_tablet":{"unit":"deg","size":"","sizes":[]},"_background_gradient_angle_mobile":{"unit":"deg","size":"","sizes":[]},"_background_hover_color_stop_tablet":{"unit":"%","size":"","sizes":[]},"_background_hover_color_stop_mobile":{"unit":"%","size":"","sizes":[]},"_background_hover_color_b_stop_tablet":{"unit":"%","size":"","sizes":[]},"_background_hover_color_b_stop_mobile":{"unit":"%","size":"","sizes":[]},"_background_hover_gradient_angle_tablet":{"unit":"deg","size":"","sizes":[]},"_background_hover_gradient_angle_mobile":{"unit":"deg","size":"","sizes":[]}},"elements":[],"isInner":false,"widgetType":"post-info","elType":"widget"},{"id":"551f9ee4","settings":{"content_width":"full","flex_direction":"row","flex_direction_tablet":"row","flex_direction_mobile":"column","flex_justify_content":"flex-end","flex_justify_content_tablet":"flex-start","flex_align_items":"center","flex_align_items_tablet":"center","flex_align_items_mobile":"flex-start","flex_gap":{"column":"20","row":"20","isLinked":true,"unit":"px","size":20},"flex_gap_mobile":{"column":"30","row":"30","isLinked":true,"unit":"px","size":30},"padding":{"unit":"px","top":"0","right":"0","bottom":"0","left":"0","isLinked":true}},"elements":[{"id":"326db898","settings":{"title":"SHARE POST","header_size":"p","title_color":"#9F9F9F","typography_typography":"custom","typography_font_family":"Manrope","typography_font_size":{"unit":"px","size":13,"sizes":[]},"typography_font_weight":"600","typography_text_transform":"uppercase","typography_line_height":{"unit":"em","size":1,"sizes":[]},"_margin":{"unit":"px","top":"-1","right":"0","bottom":"-4","left":"0","isLinked":false},"_margin_tablet":{"unit":"px","top":"-1","right":"0","bottom":"-4","left":"0","isLinked":false},"content_width":"full"},"elements":[],"isInner":false,"widgetType":"heading","elType":"widget"},{"id":"6719a0a4","settings":{"content_width":"full","share_buttons":[{"_id":"0b83db6"},{"button":"twitter","_id":"dc94077"},{"button":"vk","_id":"37dcb7c"}],"view":"icon","skin":"flat","shape":"circle","alignment":"left","button_size":{"unit":"px","size":0.85,"sizes":[]},"icon_size":{"unit":"px","size":17,"sizes":[]},"icon_size_tablet":{"unit":"px","size":"","sizes":[]},"icon_size_mobile":{"unit":"px","size":"","sizes":[]},"color_source":"custom","primary_color":"#000000","secondary_color":"#FFFFFF","primary_color_hover":"#D8D8D8","secondary_color_hover":"#000000"},"elements":[],"isInner":false,"widgetType":"share-buttons","elType":"widget"}],"isInner":true,"elType":"container"}],"isInner":true,"elType":"container"},{"id":"11ca263b","settings":{"flex_direction":"column","flex_justify_content":"flex-start","flex_align_items":"flex-start","flex_gap":{"column":"0","row":"0","isLinked":true,"unit":"px","size":0},"flex_gap_tablet":{"column":"0","row":"0","isLinked":true,"unit":"px","size":0},"padding":{"unit":"px","top":"0","right":"0","bottom":"0","left":"0","isLinked":true},"boxed_width":{"unit":"px","size":1000,"sizes":[]},"content_width":"full"},"elements":[{"id":"5c21f17e","settings":{"content_width":"full","prev_label":"Previous","next_label":"Next","arrow":"fa fa-arrow-left","show_title":"","label_color":"#9F9F9F","label_typography_typography":"custom","label_typography_font_family":"Manrope","label_typography_font_size":{"unit":"px","size":14,"sizes":[]},"label_typography_font_weight":"500","label_typography_letter_spacing":{"unit":"em","size":0.03,"sizes":[]},"label_typography_letter_spacing_tablet":{"unit":"em","size":"","sizes":[]},"label_typography_letter_spacing_mobile":{"unit":"em","size":"","sizes":[]},"arrow_color":"#000000","arrow_hover_color":"#000000","arrow_size":{"unit":"px","size":30,"sizes":[]},"arrow_padding":{"unit":"px","size":20,"sizes":[]},"sep_color":"#D8D8D8","borders_width":{"unit":"px","size":1,"sizes":[]},"borders_spacing":{"unit":"px","size":0,"sizes":[]},"_margin":{"unit":"px","top":"-9","right":"0","bottom":"-9","left":"0","isLinked":false},"_element_width":"inherit","show_borders":""},"elements":[],"isInner":false,"widgetType":"post-navigation","elType":"widget"}],"isInner":true,"elType":"container"}],"isInner":true,"elType":"container"}],"isInner":true,"elType":"container"}],"isInner":false,"elType":"container"}],"page_settings":{"page_template":"elementor_canvas","preview_type":"single\/post","preview_id":"23706"},"version":"0.4","title":"C2335-single-blog-post","type":"single-post"}